{
  "ToJson": [
    {
      "Code": "VNINDEX",
      "Min": 7.97,
      "Median": 14.1,
      "Max": 22.07,
      "KhoangGiaTri": 14.1,
      "HienTai": 13.89
    },
    {
      "Code": "China",
      "Min": 9.76,
      "Median": 14.5,
      "Max": 28.7,
      "KhoangGiaTri": 18.939999999999998,
      "HienTai": 14.34
    },
    {
      "Code": "Korea",
      "Min": 8.5,
      "Median": 14.37,
      "Max": 33,
      "KhoangGiaTri": 24.5,
      "HienTai": 13.87
    },
    {
      "Code": "India",
      "Min": 12.55,
      "Median": 22,
      "Max": 34.5,
      "KhoangGiaTri": 21.95,
      "HienTai": 21.54
    },
    {
      "Code": "Thailand",
      "Min": 6.85,
      "Median": 18.1,
      "Max": 41.25,
      "KhoangGiaTri": 34.4,
      "HienTai": 16.23
    },
    {
      "Code": "Indonesia",
      "Min": 8.63,
      "Median": 13.821,
      "Max": 21.866,
      "KhoangGiaTri": 13.24,
      "HienTai": 12.04
    },
    {
      "Code": "Philippines",
      "Min": 9.29,
      "Median": 17.7255,
      "Max": 26.282,
      "KhoangGiaTri": 16.992,
      "HienTai": 11.96
    },
    {
      "Code": "Malaysia",
      "Min": 12.15,
      "Median": 17.175,
      "Max": 29.8,
      "KhoangGiaTri": 17.65,
      "HienTai": 17.27
    },
    {
      "Code": "HongKong",
      "Min": 8,
      "Median": 11.4,
      "Max": 19.5,
      "KhoangGiaTri": 11.5,
      "HienTai": 11.95
    },
    {
      "Code": "USA",
      "Min": 13.5,
      "Median": 22.49,
      "Max": 123.73,
      "KhoangGiaTri": 110.23,
      "HienTai": 28.39
    }
  ],
  "ToJson100": [
    {
      "Code": "AAA",
      "ib": 0.4233,
      "ab": 2.0395,
      "eb": 0.78,
      "hb": 0.5463,
      "ie": 1.7767,
      "ae": 36.8575,
      "ee": 8.82,
      "he": 10.5459,
      "is": 0.1614,
      "as": 0.9448,
      "es": 0.33,
      "hs": 0.2153
    },
    {
      "Code": "ACB",
      "ib": 1.0693,
      "ab": 3.7056,
      "eb": 1.51,
      "hb": 1.3303,
      "ie": 5.0995,
      "ae": 37.9273,
      "ee": 9.06,
      "he": 6.9936,
      "is": 1.5599,
      "as": 4.7328,
      "es": 2.72,
      "hs": 2.0033
    },
    {
      "Code": "ANV",
      "ib": 0.3028,
      "ab": 2.2953,
      "eb": 0.86,
      "hb": 2.0183,
      "ie": -105.0799,
      "ae": 118.6206,
      "ee": 9.71,
      "he": 36.2752,
      "is": 0.1626,
      "as": 1.4481,
      "es": 0.55,
      "hs": 1.1818
    },
    {
      "Code": "ASM",
      "ib": 0.3555,
      "ab": 1.9722,
      "eb": 0.77,
      "hb": 0.5259,
      "ie": -44.026,
      "ae": 33.7273,
      "ee": 9.2,
      "he": 20.6711,
      "is": 0.1056,
      "as": 3.7169,
      "es": 0.44,
      "hs": 0.2346
    },
    {
      "Code": "BCG",
      "ib": 0.3016,
      "ab": 2.2282,
      "eb": 0.66,
      "hb": 0.2848,
      "ie": -96.6713,
      "ae": 62.5644,
      "ee": 10.6,
      "he": 6.0569,
      "is": 0.3119,
      "as": 45.1579,
      "es": 0.72,
      "hs": 0.5597
    },
    {
      "Code": "BCM",
      "ib": 0.0549,
      "ab": 5.2973,
      "eb": 3.46,
      "hb": 3.5594,
      "ie": 8.021,
      "ae": 154.073,
      "ee": 25.96,
      "he": 29.2517,
      "is": 0.0701,
      "as": 15.9779,
      "es": 7.71,
      "hs": 11.3237
    },
    {
      "Code": "BID",
      "ib": 1.1491,
      "ab": 2.764,
      "eb": 2.05,
      "hb": 1.7839,
      "ie": 8.2745,
      "ae": 23.339,
      "ee": 12.54,
      "he": 10.4994,
      "is": 1.5038,
      "as": 3.8968,
      "es": 2.39,
      "hs": 1.7272
    },
    {
      "Code": "BMP",
      "ib": 1.1626,
      "ab": 3.8548,
      "eb": 2.08,
      "hb": 3.8977,
      "ie": 4.1447,
      "ae": 22.5775,
      "ee": 9.32,
      "he": 10.7086,
      "is": 0.7074,
      "as": 2.6624,
      "es": 1.32,
      "hs": 2.3317
    },
    {
      "Code": "BSI",
      "ib": 0.4569,
      "ab": 2.8092,
      "eb": 0.99,
      "hb": 2.0944,
      "ie": -26.5163,
      "ae": 51.6162,
      "ee": 11.44,
      "he": 30.1334,
      "is": 1.1873,
      "as": 8.661,
      "es": 1.96,
      "hs": 7.691
    },
    {
      "Code": "BVH",
      "ib": 1.4019,
      "ab": 4.7409,
      "eb": 2.43,
      "hb": 1.7222,
      "ie": 15.1813,
      "ae": 57.8055,
      "ee": 28.09,
      "he": 18.1494,
      "is": 0,
      "as": 8.2458,
      "es": 1.09,
      "hs": 0.9977
    },
    {
      "Code": "BWE",
      "ib": 0.739,
      "ab": 2.5099,
      "eb": 1.77,
      "hb": 2.0796,
      "ie": 6.3255,
      "ae": 23.0763,
      "ee": 12.02,
      "he": 17.4547,
      "is": 1.157,
      "as": 3.1308,
      "es": 2.35,
      "hs": 2.5911
    },
    {
      "Code": "CII",
      "ib": 0.6801,
      "ab": 2.6191,
      "eb": 1.33,
      "hb": 1.0001,
      "ie": -20.9019,
      "ae": 152.8267,
      "ee": 10.05,
      "he": 339.9072,
      "is": 0.6592,
      "as": 13.6487,
      "es": 2.7,
      "hs": 1.8955
    },
    {
      "Code": "CMG",
      "ib": 0.4629,
      "ab": 3.7492,
      "eb": 1.59,
      "hb": 3.1087,
      "ie": -4.2539,
      "ae": 37.2645,
      "ee": 16.47,
      "he": 26.0627,
      "is": 0.0962,
      "as": 1.3664,
      "es": 0.35,
      "hs": 1.1078
    },
    {
      "Code": "CRE",
      "ib": 0.5661,
      "ab": 3.8255,
      "eb": 1.12,
      "hb": 0.7373,
      "ie": -122.1472,
      "ae": 1604.4212,
      "ee": 8.19,
      "he": 117.4373,
      "is": 0.5672,
      "as": 4.734,
      "es": 1.28,
      "hs": 3.4582
    },
    {
      "Code": "CTD",
      "ib": 0.3597,
      "ab": 2.633,
      "eb": 0.9,
      "hb": 0.9632,
      "ie": -66.8936,
      "ae": 278.5561,
      "ee": 9.19,
      "he": 26.0314,
      "is": 0.1875,
      "as": 1.1927,
      "es": 0.38,
      "hs": 0.3624
    },
    {
      "Code": "CTG",
      "ib": 0.9115,
      "ab": 2.5199,
      "eb": 1.32,
      "hb": 1.5801,
      "ie": 6.2752,
      "ae": 16.7319,
      "ee": 9.55,
      "he": 9.3633,
      "is": 1.0749,
      "as": 3.8311,
      "es": 2.55,
      "hs": 1.7484
    },
    {
      "Code": "CTR",
      "ib": 1.3519,
      "ab": 8.5011,
      "eb": 4.71,
      "hb": 5.84,
      "ie": 7.1717,
      "ae": 29.1708,
      "ee": 17.9,
      "he": 21.5396,
      "is": 0.2531,
      "as": 1.3515,
      "es": 0.81,
      "hs": 0.9205
    },
    {
      "Code": "DBC",
      "ib": 0.5703,
      "ab": 2.0427,
      "eb": 0.99,
      "hb": 1.5523,
      "ie": -26.529,
      "ae": 45.1134,
      "ee": 7.19,
      "he": 8.5364,
      "is": 0.1865,
      "as": 0.7542,
      "es": 0.36,
      "hs": 0.7383
    },
    {
      "Code": "DCM",
      "ib": 0.5574,
      "ab": 2.9037,
      "eb": 1.14,
      "hb": 1.7191,
      "ie": 3.1885,
      "ae": 17.9832,
      "ee": 9.05,
      "he": 12.1916,
      "is": 0.4811,
      "as": 2.2635,
      "es": 1.15,
      "hs": 1.2824
    },
    {
      "Code": "DGC",
      "ib": 0.9653,
      "ab": 6.0487,
      "eb": 2.16,
      "hb": 2.7566,
      "ie": 3.4514,
      "ae": 20.332,
      "ee": 7.91,
      "he": 12.3417,
      "is": 0.4892,
      "as": 4.7102,
      "es": 1.11,
      "hs": 3.7459
    },
    {
      "Code": "DGW",
      "ib": 0.7986,
      "ab": 7.3467,
      "eb": 1.78,
      "hb": 3.1808,
      "ie": 4.5141,
      "ae": 28.3819,
      "ee": 11.2,
      "he": 21.3035,
      "is": 0.123,
      "as": 0.6132,
      "es": 0.24,
      "hs": 0.4306
    },
    {
      "Code": "DIG",
      "ib": 0.5762,
      "ab": 7.3723,
      "eb": 1.23,
      "hb": 1.5353,
      "ie": -636.8961,
      "ae": 446.1416,
      "ee": 29.51,
      "he": 60.7023,
      "is": 1.3851,
      "as": 18.9628,
      "es": 3.02,
      "hs": 9.3892
    },
    {
      "Code": "DPM",
      "ib": 0.66,
      "ab": 3.3729,
      "eb": 1.28,
      "hb": 1.3515,
      "ie": 2.7986,
      "ae": 26.393,
      "ee": 9.12,
      "he": 31.649,
      "is": 0.6612,
      "as": 2.352,
      "es": 1.16,
      "hs": 1.0584
    },
    {
      "Code": "DXG",
      "ib": 0.6367,
      "ab": 4.4456,
      "eb": 1.27,
      "hb": 1.4436,
      "ie": -60.0585,
      "ae": 92.0036,
      "ee": 8.09,
      "he": 56.3686,
      "is": 0.7791,
      "as": 6.2019,
      "es": 1.92,
      "hs": 3.3054
    },
    {
      "Code": "DXS",
      "ib": 0.4542,
      "ab": 3.1031,
      "eb": 0.71,
      "hb": 0.9205,
      "ie": -434.3901,
      "ae": 33.3326,
      "ee": 9.81,
      "he": 37.2598,
      "is": 0.6347,
      "as": 3.8364,
      "es": 1.75,
      "hs": 2.3057
    },
    {
      "Code": "EIB",
      "ib": 0.8614,
      "ab": 2.3028,
      "eb": 1.23,
      "hb": 1.7139,
      "ie": -87.9411,
      "ae": 202.7111,
      "ee": 15.77,
      "he": 12.7663,
      "is": 1.9938,
      "as": 9.2073,
      "es": 4.2,
      "hs": 2.7579
    },
    {
      "Code": "EVF",
      "ib": 0.4071,
      "ab": 2.4615,
      "eb": 0.77,
      "hb": 0.917,
      "ie": 6.415,
      "ae": 23.3817,
      "ee": 10.13,
      "he": 12.6539,
      "is": 0.9639,
      "as": 4.2504,
      "es": 2.14,
      "hs": 1.9125
    },
    {
      "Code": "FPT",
      "ib": 1.6513,
      "ab": 7.076,
      "eb": 2.59,
      "hb": 5.7228,
      "ie": 6.2349,
      "ae": 27.2298,
      "ee": 11.11,
      "he": 22.0822,
      "is": 0.2318,
      "as": 3.3813,
      "es": 0.63,
      "hs": 2.805
    },
    {
      "Code": "FRT",
      "ib": 1.1775,
      "ab": 14.6388,
      "eb": 4.39,
      "hb": 12.0273,
      "ie": -1389.8713,
      "ae": 222.6799,
      "ee": 14.92,
      "he": 55.9956,
      "is": 0.0897,
      "as": 0.703,
      "es": 0.31,
      "hs": 0.5854
    },
    {
      "Code": "FTS",
      "ib": 0.655,
      "ab": 3.6929,
      "eb": 1.11,
      "hb": 3.2492,
      "ie": 2.579,
      "ae": 124.6039,
      "ee": 9.18,
      "he": 24.3004,
      "is": 1.9606,
      "as": 13.3023,
      "es": 4.91,
      "hs": 11.5924
    },
    {
      "Code": "GAS",
      "ib": 2.0084,
      "ab": 5.8603,
      "eb": 3.34,
      "hb": 2.5433,
      "ie": 6.7245,
      "ae": 25.6451,
      "ee": 15.09,
      "he": 15.0554,
      "is": 1.133,
      "as": 3.3003,
      "es": 2.02,
      "hs": 1.5128
    },
    {
      "Code": "GEX",
      "ib": 0.9025,
      "ab": 2.7824,
      "eb": 1.53,
      "hb": 2.5023,
      "ie": 6.1948,
      "ae": 790.042,
      "ee": 13.06,
      "he": 20.3734,
      "is": 0.3285,
      "as": 1.199,
      "es": 0.64,
      "hs": 1.0222
    },
    {
      "Code": "GMD",
      "ib": 0.4545,
      "ab": 2.8475,
      "eb": 1.22,
      "hb": 2.019,
      "ie": -13.2796,
      "ae": 404.6483,
      "ee": 14.1,
      "he": 16.0401,
      "is": 0.7537,
      "as": 6.0253,
      "es": 2.08,
      "hs": 4.0829
    },
    {
      "Code": "GVR",
      "ib": 0.5307,
      "ab": 3.127,
      "eb": 1.62,
      "hb": 2.217,
      "ie": 8.5514,
      "ae": 53.5349,
      "ee": 22.08,
      "he": 25.629,
      "is": 0.0683,
      "as": 6.2542,
      "es": 3.41,
      "hs": 4.4048
    },
    {
      "Code": "HAG",
      "ib": 0.2865,
      "ab": 4.6741,
      "eb": 1.25,
      "hb": 1.5671,
      "ie": -65.0384,
      "ae": 61.1913,
      "ee": 10.98,
      "he": 12.5002,
      "is": 0.7315,
      "as": 6.9047,
      "es": 2.04,
      "hs": 2.4048
    },
    {
      "Code": "HCM",
      "ib": 0.7629,
      "ab": 3.2668,
      "eb": 1.72,
      "hb": 2.5505,
      "ie": 5.8049,
      "ae": 108.9454,
      "ee": 12.86,
      "he": 17.8864,
      "is": 2.3014,
      "as": 11.3423,
      "es": 4.42,
      "hs": 4.0109
    },
    {
      "Code": "HDB",
      "ib": 1.0751,
      "ab": 3.1049,
      "eb": 1.53,
      "hb": 1.4488,
      "ie": 5.3952,
      "ae": 22.6351,
      "ee": 7.53,
      "he": 6.1104,
      "is": 1.0949,
      "as": 5.7994,
      "es": 2.53,
      "hs": 1.3563
    },
    {
      "Code": "HDC",
      "ib": 0.6739,
      "ab": 5.5976,
      "eb": 1.14,
      "hb": 2.0798,
      "ie": 4.5241,
      "ae": 52.9939,
      "ee": 10.7,
      "he": 59.658,
      "is": 0.9838,
      "as": 7.5937,
      "es": 1.61,
      "hs": 8.3455
    },
    {
      "Code": "HDG",
      "ib": 0.7891,
      "ab": 5.1008,
      "eb": 1.82,
      "hb": 1.5145,
      "ie": 3.3269,
      "ae": 21.7581,
      "ee": 10.24,
      "he": 33.5819,
      "is": 0.4599,
      "as": 3.6983,
      "es": 1.25,
      "hs": 3.8369
    },
    {
      "Code": "HHV",
      "ib": 0.4313,
      "ab": 1.4039,
      "eb": 0.89,
      "hb": 1.0821,
      "ie": 3.7802,
      "ae": 333.433,
      "ee": 14.19,
      "he": 11.8095,
      "is": 0.106,
      "as": 9.2472,
      "es": 1.54,
      "hs": 1.6786
    },
    {
      "Code": "HPG",
      "ib": 0.9022,
      "ab": 3.1341,
      "eb": 1.67,
      "hb": 1.6401,
      "ie": 3.5705,
      "ae": 84.2346,
      "ee": 9.05,
      "he": 15.449,
      "is": 0.433,
      "as": 2.1331,
      "es": 1.13,
      "hs": 1.3256
    },
    {
      "Code": "HSG",
      "ib": 0.4986,
      "ab": 3.246,
      "eb": 1.27,
      "hb": 0.9731,
      "ie": -11.015,
      "ae": 225.095,
      "ee": 7.04,
      "he": 23.6385,
      "is": 0.0916,
      "as": 1.1231,
      "es": 0.3,
      "hs": 0.2762
    },
    {
      "Code": "HT1",
      "ib": 0.4073,
      "ab": 2.0482,
      "eb": 1.09,
      "hb": 1.0293,
      "ie": -29.1146,
      "ae": 780.4376,
      "ee": 11.7,
      "he": 66.0711,
      "is": 0.1374,
      "as": 1.2289,
      "es": 0.67,
      "hs": 0.7165
    },
    {
      "Code": "IMP",
      "ib": 0.7814,
      "ab": 3.3918,
      "eb": 1.64,
      "hb": 3.6111,
      "ie": 6.4128,
      "ae": 26.4727,
      "ee": 15.95,
      "he": 24.3437,
      "is": 0.6818,
      "as": 3.7485,
      "es": 1.88,
      "hs": 3.5165
    },
    {
      "Code": "KBC",
      "ib": 0.4981,
      "ab": 3.2243,
      "eb": 0.97,
      "hb": 1.3342,
      "ie": -9.5142,
      "ae": 104.622,
      "ee": 11.64,
      "he": 16.9991,
      "is": 2.0606,
      "as": 14.2437,
      "es": 5.24,
      "hs": 3.7027
    },
    {
      "Code": "KDC",
      "ib": 0.6072,
      "ab": 2.539,
      "eb": 1.71,
      "hb": 2.4747,
      "ie": -323.7666,
      "ae": 146.4532,
      "ee": 19.26,
      "he": -381.4752,
      "is": 0.5248,
      "as": 3.7804,
      "es": 1.61,
      "hs": 1.8447
    },
    {
      "Code": "KDH",
      "ib": 0.3533,
      "ab": 3.1846,
      "eb": 1.74,
      "hb": 1.7808,
      "ie": -8.8995,
      "ae": 65.7359,
      "ee": 15.94,
      "he": 34.4119,
      "is": 1.5288,
      "as": 17.7492,
      "es": 4.51,
      "hs": 8.1827
    },
    {
      "Code": "KOS",
      "ib": 1.6534,
      "ab": 3.931,
      "eb": 3.24,
      "hb": 3.6067,
      "ie": 28.1651,
      "ae": 542.6356,
      "ee": 157.71,
      "he": 394.2036,
      "is": 1.9117,
      "as": 6.9586,
      "es": 3.97,
      "hs": 5.8428
    },
    {
      "Code": "LPB",
      "ib": 0.5323,
      "ab": 2.3248,
      "eb": 1.05,
      "hb": 2.1686,
      "ie": 3.7345,
      "ae": 11.4817,
      "ee": 6.98,
      "he": 9.9915,
      "is": 0.7928,
      "as": 3.2302,
      "es": 1.68,
      "hs": 2.6086
    },
    {
      "Code": "MBB",
      "ib": 0.881,
      "ab": 2.12,
      "eb": 1.14,
      "hb": 1.3611,
      "ie": 3.832,
      "ae": 13.2415,
      "ee": 6.61,
      "he": 6.5325,
      "is": 1.1857,
      "as": 3.7627,
      "es": 2.12,
      "hs": 1.8451
    },
    {
      "Code": "MSB",
      "ib": 0.7945,
      "ab": 1.9373,
      "eb": 0.95,
      "hb": 0.8787,
      "ie": 5.1195,
      "ae": 13.2223,
      "ee": 6.3,
      "he": 5.9756,
      "is": 1.2849,
      "as": 4.1798,
      "es": 1.67,
      "hs": 1.5715
    },
    {
      "Code": "MSN",
      "ib": 1.6067,
      "ab": 8.5591,
      "eb": 4.11,
      "hb": 3.597,
      "ie": -474.3235,
      "ae": 232.7936,
      "ee": 30.69,
      "he": 50.6471,
      "is": 1.1203,
      "as": 9.3405,
      "es": 2.26,
      "hs": 1.3926
    },
    {
      "Code": "MWG",
      "ib": 2.3923,
      "ab": 8.4773,
      "eb": 4.44,
      "hb": 3.4312,
      "ie": 9.4141,
      "ae": 93.1969,
      "ee": 15.8,
      "he": 22.8497,
      "is": 0.3554,
      "as": 1.1423,
      "es": 0.58,
      "hs": 0.7177
    },
    {
      "Code": "NKG",
      "ib": 0.3696,
      "ab": 1.9875,
      "eb": 0.97,
      "hb": 0.8337,
      "ie": -32.5178,
      "ae": 31.8754,
      "ee": 4.86,
      "he": 12.4754,
      "is": 0.0652,
      "as": 0.4485,
      "es": 0.16,
      "hs": 0.2367
    },
    {
      "Code": "NLG",
      "ib": 1.0854,
      "ab": 2.3544,
      "eb": 1.49,
      "hb": 1.5542,
      "ie": 6.4877,
      "ae": 89.2337,
      "ee": 15.53,
      "he": 21.621,
      "is": 1.3794,
      "as": 6.8657,
      "es": 2.72,
      "hs": 1.8354
    },
    {
      "Code": "NT2",
      "ib": 0.3871,
      "ab": 2.1035,
      "eb": 1.5,
      "hb": 1.4193,
      "ie": -0.3029,
      "ae": 199.9417,
      "ee": 10.83,
      "he": 20.3986,
      "is": 0.2348,
      "as": 23.4871,
      "es": 1.03,
      "hs": 0.7978
    },
    {
      "Code": "NVL",
      "ib": 0.5354,
      "ab": 4.8574,
      "eb": 2.8,
      "hb": 0.7964,
      "ie": -56.0005,
      "ae": 52.5728,
      "ee": 21.76,
      "he": -4.7589,
      "is": 2.1318,
      "as": 17.7786,
      "es": 5.27,
      "hs": 2.9671
    },
    {
      "Code": "OCB",
      "ib": 0.796,
      "ab": 1.8343,
      "eb": 1.01,
      "hb": 0.9745,
      "ie": 5.3261,
      "ae": 9.7849,
      "ee": 7.28,
      "he": 10.7637,
      "is": 1.3606,
      "as": 4.2029,
      "es": 1.6,
      "hs": 1.6051
    },
    {
      "Code": "PAN",
      "ib": 0.5534,
      "ab": 2.6229,
      "eb": 1.3,
      "hb": 1.1708,
      "ie": 2.941,
      "ae": 32.2546,
      "ee": 14.53,
      "he": 9.5376,
      "is": 0.2625,
      "as": 2.8239,
      "es": 0.76,
      "hs": 0.3585
    },
    {
      "Code": "PC1",
      "ib": 0.6952,
      "ab": 2.026,
      "eb": 1.42,
      "hb": 1.4453,
      "ie": 6.0643,
      "ae": 56.7679,
      "ee": 12.43,
      "he": 18.2333,
      "is": 0.4112,
      "as": 1.3096,
      "es": 0.84,
      "hs": 0.8243
    },
    {
      "Code": "PDR",
      "ib": 0.992,
      "ab": 7.4169,
      "eb": 1.94,
      "hb": 1.5682,
      "ie": 7.9138,
      "ae": 651.2823,
      "ee": 20.98,
      "he": 106.5263,
      "is": 2.1328,
      "as": 66.0318,
      "es": 8.52,
      "hs": 14.8621
    },
    {
      "Code": "PHR",
      "ib": 0.6424,
      "ab": 3.6633,
      "eb": 1.67,
      "hb": 2.1493,
      "ie": 2.7706,
      "ae": 19.3872,
      "ee": 7.88,
      "he": 17.2694,
      "is": 0.8578,
      "as": 6.1311,
      "es": 2.22,
      "hs": 5.1401
    },
    {
      "Code": "PLX",
      "ib": 1.658,
      "ab": 5.1755,
      "eb": 2.83,
      "hb": 1.8417,
      "ie": 12.759,
      "ae": 71.6092,
      "ee": 18.88,
      "he": 24.692,
      "is": 0.1476,
      "as": 0.6172,
      "es": 0.35,
      "hs": 0.174
    },
    {
      "Code": "PNJ",
      "ib": 1.4672,
      "ab": 5.9856,
      "eb": 2.9,
      "hb": 2.3708,
      "ie": 6.3419,
      "ae": 29.2648,
      "ee": 14.88,
      "he": 13.4815,
      "is": 0.1217,
      "as": 1.4383,
      "es": 0.78,
      "hs": 0.7938
    },
    {
      "Code": "POW",
      "ib": 0.7847,
      "ab": 1.5213,
      "eb": 1,
      "hb": 0.9769,
      "ie": 9.393,
      "ae": 35.4545,
      "ee": 17.37,
      "he": 24.7179,
      "is": 0.2834,
      "as": 1.5301,
      "es": 1,
      "hs": 0.9815
    },
    {
      "Code": "PPC",
      "ib": 0.5659,
      "ab": 2.2845,
      "eb": 1.16,
      "hb": 0.7986,
      "ie": -102.6329,
      "ae": 534.2796,
      "ee": 7.41,
      "he": 11.3509,
      "is": 0.4863,
      "as": 2.2734,
      "es": 0.95,
      "hs": 0.5062
    },
    {
      "Code": "PTB",
      "ib": 0.7846,
      "ab": 3.9514,
      "eb": 1.82,
      "hb": 1.2248,
      "ie": 2.5599,
      "ae": 14.5761,
      "ee": 7.51,
      "he": 9.1923,
      "is": 0.0758,
      "as": 0.8946,
      "es": 0.59,
      "hs": 0.5426
    },
    {
      "Code": "PVD",
      "ib": 0.3281,
      "ab": 4.5981,
      "eb": 0.92,
      "hb": 0.7184,
      "ie": -215.9997,
      "ae": 2803.28,
      "ee": 12.8,
      "he": 16.6171,
      "is": 0.627,
      "as": 3.3344,
      "es": 1.43,
      "hs": 1.2741
    },
    {
      "Code": "PVT",
      "ib": 0.3791,
      "ab": 2.1535,
      "eb": 1.13,
      "hb": 1.0809,
      "ie": 4.7708,
      "ae": 179.8366,
      "ee": 9.6,
      "he": 7.9604,
      "is": 0.219,
      "as": 1.7441,
      "es": 0.65,
      "hs": 0.7159
    },
    {
      "Code": "REE",
      "ib": 0.7818,
      "ab": 1.9765,
      "eb": 1.36,
      "hb": 1.8744,
      "ie": 5.0476,
      "ae": 17.5131,
      "ee": 8.15,
      "he": 17.2087,
      "is": 1.3763,
      "as": 4.2292,
      "es": 2.55,
      "hs": 4.2418
    },
    {
      "Code": "SAB",
      "ib": 2.6622,
      "ab": 12.54,
      "eb": 5.47,
      "hb": 2.5636,
      "ie": 15.1851,
      "ae": 41.2128,
      "ee": 25.84,
      "he": 14.952,
      "is": 2.0603,
      "as": 5.5491,
      "es": 3.8,
      "hs": 2.0227
    },
    {
      "Code": "SBT",
      "ib": 0.8485,
      "ab": 2.46,
      "eb": 1.2,
      "hb": 1.5877,
      "ie": 3.3026,
      "ae": 36.0844,
      "ee": 15.12,
      "he": 19.8035,
      "is": 0.3335,
      "as": 2.9126,
      "es": 0.95,
      "hs": 0.5386
    },
    {
      "Code": "SCS",
      "ib": 4.1187,
      "ab": 11.9732,
      "eb": 6.11,
      "hb": 4.2401,
      "ie": 9.1738,
      "ae": 26.3895,
      "ee": 15.33,
      "he": 9.5875,
      "is": 6.01,
      "as": 16.0574,
      "es": 9.5,
      "hs": 6.2908
    },
    {
      "Code": "SHB",
      "ib": 0,
      "ab": 2.3847,
      "eb": 0.73,
      "hb": 0.949,
      "ie": -20.0178,
      "ae": 30.7735,
      "ee": 5.87,
      "he": 6.071,
      "is": 0.7108,
      "as": 12.5448,
      "es": 1.94,
      "hs": 1.1002
    },
    {
      "Code": "SIP",
      "ib": 1.8961,
      "ab": 7.1244,
      "eb": 3.93,
      "hb": 3.1864,
      "ie": 7.6656,
      "ae": 33.316,
      "ee": 13.18,
      "he": 11.6849,
      "is": 1.0489,
      "as": 3.169,
      "es": 2.04,
      "hs": 1.8829
    },
    {
      "Code": "SJS",
      "ib": 0.7823,
      "ab": 5.071,
      "eb": 1.49,
      "hb": 3.9645,
      "ie": -41.4348,
      "ae": 224.0915,
      "ee": 22.95,
      "he": 41.393,
      "is": -117.4801,
      "as": 45.3846,
      "es": 5.24,
      "hs": 17.9905
    },
    {
      "Code": "SSB",
      "ib": 1.3488,
      "ab": 3.4817,
      "eb": 2.42,
      "hb": 1.4151,
      "ie": 7.3421,
      "ae": 28.4527,
      "ee": 16.25,
      "he": 7.6613,
      "is": 2.1789,
      "as": 9.8836,
      "es": 3.79,
      "hs": 2.3741
    },
    {
      "Code": "SSI",
      "ib": 0.94,
      "ab": 3.3622,
      "eb": 1.6,
      "hb": 2.0719,
      "ie": 7.7715,
      "ae": 56.1305,
      "ee": 14.5,
      "he": 18.7399,
      "is": 2.4921,
      "as": 13.5526,
      "es": 6.07,
      "hs": 6.2671
    },
    {
      "Code": "STB",
      "ib": 0.5537,
      "ab": 2.0503,
      "eb": 1.18,
      "hb": 1.5525,
      "ie": 5.978,
      "ae": 55.198,
      "ee": 9.67,
      "he": 8.262,
      "is": 0.9104,
      "as": 5.5833,
      "es": 2.5,
      "hs": 1.5664
    },
    {
      "Code": "SZC",
      "ib": 1.1414,
      "ab": 5.0696,
      "eb": 2.38,
      "hb": 2.0466,
      "ie": 10.4005,
      "ae": 27.1838,
      "ee": 18.34,
      "he": 18.046,
      "is": 3.1552,
      "as": 10.609,
      "es": 6.03,
      "hs": 6.1227
    },
    {
      "Code": "TCB",
      "ib": 0.7853,
      "ab": 2.3387,
      "eb": 1.27,
      "hb": 1.6243,
      "ie": 4.4881,
      "ae": 12.3808,
      "ee": 8.39,
      "he": 11.5482,
      "is": 1.6575,
      "as": 6.0397,
      "es": 3.31,
      "hs": 3.4448
    },
    {
      "Code": "TCH",
      "ib": 0.5911,
      "ab": 2.4057,
      "eb": 1.46,
      "hb": 1.597,
      "ie": 7.3644,
      "ae": 31.5014,
      "ee": 16.15,
      "he": 18.2108,
      "is": 1.5846,
      "as": 10.1238,
      "es": 3.54,
      "hs": 3.3359
    },
    {
      "Code": "TLG",
      "ib": 0.6255,
      "ab": 4.7267,
      "eb": 1.86,
      "hb": 1.9598,
      "ie": 3.4154,
      "ae": 19.0671,
      "ee": 10.84,
      "he": 10.5145,
      "is": 0.2889,
      "as": 2.1053,
      "es": 1.12,
      "hs": 1.2699
    },
    {
      "Code": "TPB",
      "ib": 0.9199,
      "ab": 2.4955,
      "eb": 1.4,
      "hb": 0.9935,
      "ie": 5.1289,
      "ae": 13.734,
      "ee": 8.27,
      "he": 6.2319,
      "is": 1.1568,
      "as": 4.7392,
      "es": 2.22,
      "hs": 1.2725
    },
    {
      "Code": "VCB",
      "ib": 1.1081,
      "ab": 4.5795,
      "eb": 2.81,
      "hb": 2.5046,
      "ie": 8.9085,
      "ae": 26.3124,
      "ee": 16.11,
      "he": 15.1126,
      "is": 3.5773,
      "as": 7.9055,
      "es": 5.25,
      "hs": 4.7992
    },
    {
      "Code": "VCG",
      "ib": 0.7,
      "ab": 3.4169,
      "eb": 1.49,
      "hb": 1.823,
      "ie": 6.0716,
      "ae": 73.4574,
      "ee": 15.56,
      "he": 25.252,
      "is": 0.2334,
      "as": 3.5446,
      "es": 0.82,
      "hs": 1.1652
    },
    {
      "Code": "VCI",
      "ib": 0.8935,
      "ab": 4.375,
      "eb": 2.21,
      "hb": 2.2057,
      "ie": 5.2567,
      "ae": 52.2719,
      "ee": 13.05,
      "he": 23.9709,
      "is": 2.2622,
      "as": 8.6874,
      "es": 5.43,
      "hs": 6.4591
    },
    {
      "Code": "VGC",
      "ib": 0.8317,
      "ab": 3.5593,
      "eb": 1.78,
      "hb": 2.3888,
      "ie": 7.451,
      "ae": 30.8571,
      "ee": 14.53,
      "he": 16.8409,
      "is": 0.2708,
      "as": 2.2309,
      "es": 1.12,
      "hs": 1.694
    },
    {
      "Code": "VHC",
      "ib": 0.9259,
      "ab": 3.0646,
      "eb": 1.7,
      "hb": 1.4958,
      "ie": 4.2899,
      "ae": 19.411,
      "ee": 8.42,
      "he": 10.6156,
      "is": 0.2901,
      "as": 1.6236,
      "es": 0.66,
      "hs": 1.0781
    },
    {
      "Code": "VHM",
      "ib": 0.8562,
      "ab": 8.2529,
      "eb": 3.19,
      "hb": 1.7204,
      "ie": 3.0228,
      "ae": 8345.338,
      "ee": 10.85,
      "he": 11.074,
      "is": 0.5349,
      "as": 4080,
      "es": 3.96,
      "hs": 3.389
    },
    {
      "Code": "VIB",
      "ib": 1.0218,
      "ab": 3.3639,
      "eb": 1.44,
      "hb": 1.3038,
      "ie": 4.2959,
      "ae": 21.4934,
      "ee": 7.39,
      "he": 7.9579,
      "is": 1.2343,
      "as": 5.3869,
      "es": 2.39,
      "hs": 1.5733
    },
    {
      "Code": "VIC",
      "ib": 1.2105,
      "ab": 9.4617,
      "eb": 4.25,
      "hb": 2.7001,
      "ie": -123.8555,
      "ae": 113.2229,
      "ee": 42.26,
      "he": 35.9964,
      "is": 1.0067,
      "as": 41.4898,
      "es": 2.88,
      "hs": 1.5676
    },
    {
      "Code": "VIX",
      "ib": 0.4086,
      "ab": 2.5588,
      "eb": 0.86,
      "hb": 1.4552,
      "ie": -15.8542,
      "ae": 114.6497,
      "ee": 7.97,
      "he": 23.421,
      "is": 1.3285,
      "as": 10.5311,
      "es": 3.59,
      "hs": 8.3283
    },
    {
      "Code": "VJC",
      "ib": 2.9142,
      "ab": 8.7904,
      "eb": 4.14,
      "hb": 3.19,
      "ie": -153.2493,
      "ae": 966.4094,
      "ee": 19.48,
      "he": 34.7451,
      "is": 0.6751,
      "as": 5.209,
      "es": 1.39,
      "hs": 0.7254
    },
    {
      "Code": "VND",
      "ib": 0.7124,
      "ab": 4.3937,
      "eb": 1.16,
      "hb": 1.3483,
      "ie": -403.2384,
      "ae": 37.1359,
      "ee": 9.15,
      "he": 17.4443,
      "is": 1.6186,
      "as": 6.9976,
      "es": 3.47,
      "hs": 4.9798
    },
    {
      "Code": "VNM",
      "ib": 3.5088,
      "ab": 11.2389,
      "eb": 5.5,
      "hb": 3.7027,
      "ie": 9.2368,
      "ae": 26.1071,
      "ee": 17.47,
      "he": 14.2332,
      "is": 2.0108,
      "as": 5.314,
      "es": 3.11,
      "hs": 2.0588
    },
    {
      "Code": "VPB",
      "ib": 1.0013,
      "ab": 3.095,
      "eb": 1.39,
      "hb": 1.0965,
      "ie": 5.562,
      "ae": 14.6539,
      "ee": 9.34,
      "he": 9.9254,
      "is": 1.3466,
      "as": 3.9938,
      "es": 1.72,
      "hs": 1.6676
    },
    {
      "Code": "VPI",
      "ib": 2.5315,
      "ab": 4.6899,
      "eb": 3.51,
      "hb": 3.4057,
      "ie": 9.5388,
      "ae": 84.2439,
      "ee": 22.91,
      "he": 42.684,
      "is": 2.0519,
      "as": 26.9261,
      "es": 6.21,
      "hs": 7.9731
    },
    {
      "Code": "VRE",
      "ib": 0.9594,
      "ab": 4.0211,
      "eb": 2.21,
      "hb": 1.4999,
      "ie": 9.4422,
      "ae": 68.0023,
      "ee": 27.56,
      "he": 15.4268,
      "is": 4.148,
      "as": 17.0532,
      "es": 8.17,
      "hs": 7.3331
    },
    {
      "Code": "VSH",
      "ib": 0.74,
      "ab": 2.5697,
      "eb": 1.22,
      "hb": 2.4219,
      "ie": 5.4975,
      "ae": 49.7953,
      "ee": 12.17,
      "he": 16.3416,
      "is": 2.9658,
      "as": 13.3511,
      "es": 6.56,
      "hs": 5.5679
    },
    {
      "Code": "CTS",
      "ib": 0.511,
      "ab": 2.9214,
      "eb": 0.84,
      "hb": 2.6599,
      "ie": -29.3846,
      "ae": 111.5913,
      "ee": 9.82,
      "he": 26.3939,
      "is": 1.4201,
      "as": 5.7308,
      "es": 3.31,
      "hs": 5.3478
    },
    {
      "Code": "DSE",
      "ib": 1.7326,
      "ab": 2.1824,
      "eb": 2,
      "hb": 1.9772,
      "ie": 30.3466,
      "ae": 48.1846,
      "ee": 34.09,
      "he": 47.6944,
      "is": 8.1806,
      "as": 11.0665,
      "es": 10.14,
      "hs": 9.0373
    },
    {
      "Code": "NAB",
      "ib": 0.6004,
      "ab": 1.4042,
      "eb": 1.12,
      "hb": 1.2562,
      "ie": 3.9043,
      "ae": 10.3143,
      "ee": 6.32,
      "he": 6.61,
      "is": 0.5664,
      "as": 2.7009,
      "es": 1.22,
      "hs": 1.3338
    },
    {
      "Code": "VTP",
      "ib": 2.1249,
      "ab": 11.8519,
      "eb": 6.54,
      "hb": 9.0599,
      "ie": 10.9748,
      "ae": 48.4166,
      "ee": 21.85,
      "he": 37.7434,
      "is": 0.1393,
      "as": 1.5716,
      "es": 0.49,
      "hs": 0.7047
    }
  ],
  "ToJsonNH": [
    {
      "Code": "VCB",
      "ib": 1.1081,
      "ab": 4.5795,
      "eb": 2.81,
      "hb": 2.5046,
      "ie": 8.9085,
      "ae": 26.3124,
      "ee": 16.11,
      "he": 15.1126,
      "is": 3.5773,
      "as": 7.9055,
      "es": 5.25,
      "hs": 4.7992
    },
    {
      "Code": "CTG",
      "ib": 0.9115,
      "ab": 2.5199,
      "eb": 1.32,
      "hb": 1.5801,
      "ie": 6.2752,
      "ae": 16.7319,
      "ee": 9.55,
      "he": 9.3633,
      "is": 1.0749,
      "as": 3.8311,
      "es": 2.55,
      "hs": 1.7484
    },
    {
      "Code": "BID",
      "ib": 1.1491,
      "ab": 2.764,
      "eb": 2.05,
      "hb": 1.7839,
      "ie": 8.2745,
      "ae": 23.339,
      "ee": 12.54,
      "he": 10.4994,
      "is": 1.5038,
      "as": 3.8968,
      "es": 2.39,
      "hs": 1.7272
    },
    {
      "Code": "ACB",
      "ib": 1.0693,
      "ab": 3.7056,
      "eb": 1.51,
      "hb": 1.3303,
      "ie": 5.0995,
      "ae": 37.9273,
      "ee": 9.06,
      "he": 6.9936,
      "is": 1.5599,
      "as": 4.7328,
      "es": 2.72,
      "hs": 2.0033
    },
    {
      "Code": "MBB",
      "ib": 0.881,
      "ab": 2.12,
      "eb": 1.14,
      "hb": 1.3611,
      "ie": 3.832,
      "ae": 13.2415,
      "ee": 6.61,
      "he": 6.5325,
      "is": 1.1857,
      "as": 3.7627,
      "es": 2.12,
      "hs": 1.8451
    },
    {
      "Code": "STB",
      "ib": 0.5537,
      "ab": 2.0503,
      "eb": 1.18,
      "hb": 1.5525,
      "ie": 5.978,
      "ae": 55.198,
      "ee": 9.67,
      "he": 8.262,
      "is": 0.9104,
      "as": 5.5833,
      "es": 2.5,
      "hs": 1.5664
    },
    {
      "Code": "TCB",
      "ib": 0.7853,
      "ab": 2.3387,
      "eb": 1.27,
      "hb": 1.6243,
      "ie": 4.4881,
      "ae": 12.3808,
      "ee": 8.39,
      "he": 11.5482,
      "is": 1.6575,
      "as": 6.0397,
      "es": 3.31,
      "hs": 3.4448
    },
    {
      "Code": "TPB",
      "ib": 0.9199,
      "ab": 2.4955,
      "eb": 1.4,
      "hb": 0.9935,
      "ie": 5.1289,
      "ae": 13.734,
      "ee": 8.27,
      "he": 6.2319,
      "is": 1.1568,
      "as": 4.7392,
      "es": 2.22,
      "hs": 1.2725
    },
    {
      "Code": "VIB",
      "ib": 1.0218,
      "ab": 3.3639,
      "eb": 1.44,
      "hb": 1.3038,
      "ie": 4.2959,
      "ae": 21.4934,
      "ee": 7.39,
      "he": 7.9579,
      "is": 1.2343,
      "as": 5.3869,
      "es": 2.39,
      "hs": 1.5733
    },
    {
      "Code": "VPB",
      "ib": 1.0013,
      "ab": 3.095,
      "eb": 1.39,
      "hb": 1.0965,
      "ie": 5.562,
      "ae": 14.6539,
      "ee": 9.34,
      "he": 9.9254,
      "is": 1.3466,
      "as": 3.9938,
      "es": 1.72,
      "hs": 1.6676
    },
    {
      "Code": "HDB",
      "ib": 1.0751,
      "ab": 3.1049,
      "eb": 1.53,
      "hb": 1.4488,
      "ie": 5.3952,
      "ae": 22.6351,
      "ee": 7.53,
      "he": 6.1104,
      "is": 1.0949,
      "as": 5.7994,
      "es": 2.53,
      "hs": 1.3563
    },
    {
      "Code": "SHB",
      "ib": 0,
      "ab": 2.3847,
      "eb": 0.73,
      "hb": 0.949,
      "ie": -20.0178,
      "ae": 30.7735,
      "ee": 5.87,
      "he": 6.071,
      "is": 0.7108,
      "as": 12.5448,
      "es": 1.94,
      "hs": 1.1002
    },
    {
      "Code": "EIB",
      "ib": 0.8614,
      "ab": 2.3028,
      "eb": 1.23,
      "hb": 1.7139,
      "ie": -87.9411,
      "ae": 202.7111,
      "ee": 15.77,
      "he": 12.7663,
      "is": 1.9938,
      "as": 9.2073,
      "es": 4.2,
      "hs": 2.7579
    },
    {
      "Code": "LPB",
      "ib": 0.5323,
      "ab": 2.3248,
      "eb": 1.05,
      "hb": 2.1686,
      "ie": 3.7345,
      "ae": 11.4817,
      "ee": 6.98,
      "he": 9.9915,
      "is": 0.7928,
      "as": 3.2302,
      "es": 1.68,
      "hs": 2.6086
    },
    {
      "Code": "BAB",
      "ib": 0.9178,
      "ab": 2.2386,
      "eb": 1.51,
      "hb": 1.0298,
      "ie": 10.1947,
      "ae": 30.117,
      "ee": 16.25,
      "he": 10.9422,
      "is": 0.812,
      "as": 8.7391,
      "es": 5.54,
      "hs": 0.9312
    },
    {
      "Code": "KLB",
      "ib": 0.6521,
      "ab": 2.1953,
      "eb": 0.87,
      "hb": 0.9466,
      "ie": -864.8188,
      "ae": 101.7222,
      "ee": 12.93,
      "he": 6.4597,
      "is": 0.5092,
      "as": 5.4461,
      "es": 2.55,
      "hs": 0.8048
    },
    {
      "Code": "NVB",
      "ib": 0.4387,
      "ab": 3.3208,
      "eb": 0.78,
      "hb": 2.9537,
      "ie": -1854.5606,
      "ae": 91330.9863,
      "ee": 72.77,
      "he": -2.4493,
      "is": 0.8525,
      "as": 10.1409,
      "es": 2.8,
      "hs": 3.4122
    },
    {
      "Code": "ABB",
      "ib": 0.5388,
      "ab": 1.3962,
      "eb": 0.65,
      "hb": 0.6331,
      "ie": 4.3752,
      "ae": 323.1641,
      "ee": 8.75,
      "he": 12.6552,
      "is": 0.6781,
      "as": 3.5123,
      "es": 0.88,
      "hs": 0.8823
    },
    {
      "Code": "BVB",
      "ib": 0.6924,
      "ab": 1.8389,
      "eb": 1.06,
      "hb": 1.3812,
      "ie": 10.9538,
      "ae": 92.3797,
      "ee": 24.55,
      "he": 23.8213,
      "is": 0.6639,
      "as": 5.4163,
      "es": 1.14,
      "hs": 1.0909
    },
    {
      "Code": "MSB",
      "ib": 0.7945,
      "ab": 1.9373,
      "eb": 0.95,
      "hb": 0.8787,
      "ie": 5.1195,
      "ae": 13.2223,
      "ee": 6.3,
      "he": 5.9756,
      "is": 1.2849,
      "as": 4.1798,
      "es": 1.67,
      "hs": 1.5715
    },
    {
      "Code": "NAB",
      "ib": 0.6004,
      "ab": 1.4042,
      "eb": 1.12,
      "hb": 1.2562,
      "ie": 3.9043,
      "ae": 10.3143,
      "ee": 6.32,
      "he": 6.61,
      "is": 0.5664,
      "as": 2.7009,
      "es": 1.22,
      "hs": 1.3338
    },
    {
      "Code": "OCB",
      "ib": 0.796,
      "ab": 1.8343,
      "eb": 1.01,
      "hb": 0.9745,
      "ie": 5.3261,
      "ae": 9.7849,
      "ee": 7.28,
      "he": 10.7637,
      "is": 1.3606,
      "as": 4.2029,
      "es": 1.6,
      "hs": 1.6051
    },
    {
      "Code": "PGB",
      "ib": 1.0476,
      "ab": 2.3047,
      "eb": 1.48,
      "hb": 1.3438,
      "ie": 13.246,
      "ae": 41.075,
      "ee": 25.25,
      "he": 22.3822,
      "is": 1.5853,
      "as": 8.918,
      "es": 2.54,
      "hs": 1.6358
    },
    {
      "Code": "SGB",
      "ib": 0.9709,
      "ab": 1.6006,
      "eb": 1.08,
      "hb": 1.0412,
      "ie": 15.7216,
      "ae": 56.6391,
      "ee": 26.1,
      "he": 44.5257,
      "is": 1.5899,
      "as": 7.7974,
      "es": 2.18,
      "hs": 1.9407
    },
    {
      "Code": "SSB",
      "ib": 1.3488,
      "ab": 3.4817,
      "eb": 2.42,
      "hb": 1.4151,
      "ie": 7.3421,
      "ae": 28.4527,
      "ee": 16.25,
      "he": 7.6613,
      "is": 2.1789,
      "as": 9.8836,
      "es": 3.79,
      "hs": 2.3741
    },
    {
      "Code": "VAB",
      "ib": 0.466,
      "ab": 1.3233,
      "eb": 0.61,
      "hb": 0.8912,
      "ie": 4.1737,
      "ae": 14.8683,
      "ee": 6.04,
      "he": 8.5205,
      "is": 0.4365,
      "as": 4.6761,
      "es": 0.68,
      "hs": 1.0619
    },
    {
      "Code": "VBB",
      "ib": 0.6472,
      "ab": 1.6343,
      "eb": 0.91,
      "hb": 0.9684,
      "ie": 6.118,
      "ae": 30.4702,
      "ee": 10.71,
      "he": 8.2542,
      "is": 0.4955,
      "as": 5.4488,
      "es": 2.01,
      "hs": 0.8222
    }
  ],
  "ToJsonCK": [
    {
      "Code": "SSI",
      "ib": 0.94,
      "ab": 3.3622,
      "eb": 1.6,
      "hb": 2.0719,
      "ie": 7.7715,
      "ae": 56.1305,
      "ee": 14.5,
      "he": 18.7399,
      "is": 2.4921,
      "as": 13.5526,
      "es": 6.07,
      "hs": 6.2671
    },
    {
      "Code": "VND",
      "ib": 0.7124,
      "ab": 4.3937,
      "eb": 1.16,
      "hb": 1.3483,
      "ie": -403.2384,
      "ae": 37.1359,
      "ee": 9.15,
      "he": 17.4443,
      "is": 1.6186,
      "as": 6.9976,
      "es": 3.47,
      "hs": 4.9798
    },
    {
      "Code": "HCM",
      "ib": 0.7629,
      "ab": 3.2668,
      "eb": 1.72,
      "hb": 2.5505,
      "ie": 5.8049,
      "ae": 108.9454,
      "ee": 12.86,
      "he": 17.8864,
      "is": 2.3014,
      "as": 11.3423,
      "es": 4.42,
      "hs": 4.0109
    },
    {
      "Code": "VCI",
      "ib": 0.8935,
      "ab": 4.375,
      "eb": 2.21,
      "hb": 2.2057,
      "ie": 5.2567,
      "ae": 52.2719,
      "ee": 13.05,
      "he": 23.9709,
      "is": 2.2622,
      "as": 8.6874,
      "es": 5.43,
      "hs": 6.4591
    },
    {
      "Code": "MBS",
      "ib": 0.4704,
      "ab": 3.1861,
      "eb": 1.4,
      "hb": 2.2659,
      "ie": -120.0871,
      "ae": 95.1425,
      "ee": 15.13,
      "he": 17.2146,
      "is": 1.1983,
      "as": 6.7464,
      "es": 2.31,
      "hs": 4.586
    },
    {
      "Code": "SHS",
      "ib": 0.4841,
      "ab": 3.7583,
      "eb": 0.95,
      "hb": 1.1068,
      "ie": -74.9507,
      "ae": 62.7179,
      "ee": 8.2,
      "he": 13.9689,
      "is": 0.9904,
      "as": 13.3257,
      "es": 2.42,
      "hs": 6.6418
    },
    {
      "Code": "VIX",
      "ib": 0.4086,
      "ab": 2.5588,
      "eb": 0.86,
      "hb": 1.4552,
      "ie": -15.8542,
      "ae": 114.6497,
      "ee": 7.97,
      "he": 23.421,
      "is": 1.3285,
      "as": 10.5311,
      "es": 3.59,
      "hs": 8.3283
    },
    {
      "Code": "FTS",
      "ib": 0.655,
      "ab": 3.6929,
      "eb": 1.11,
      "hb": 3.2492,
      "ie": 2.579,
      "ae": 124.6039,
      "ee": 9.18,
      "he": 24.3004,
      "is": 1.9606,
      "as": 13.3023,
      "es": 4.91,
      "hs": 11.5924
    },
    {
      "Code": "BSI",
      "ib": 0.4569,
      "ab": 2.8092,
      "eb": 0.99,
      "hb": 2.0944,
      "ie": -26.5163,
      "ae": 51.6162,
      "ee": 11.44,
      "he": 30.1334,
      "is": 1.1873,
      "as": 8.661,
      "es": 1.96,
      "hs": 7.691
    },
    {
      "Code": "CTS",
      "ib": 0.511,
      "ab": 2.9214,
      "eb": 0.84,
      "hb": 2.6599,
      "ie": -29.3846,
      "ae": 111.5913,
      "ee": 9.82,
      "he": 26.3939,
      "is": 1.4201,
      "as": 5.7308,
      "es": 3.31,
      "hs": 5.3478
    },
    {
      "Code": "AGR",
      "ib": 0.2966,
      "ab": 2.2479,
      "eb": 0.64,
      "hb": 1.4572,
      "ie": -44.9647,
      "ae": 85.3736,
      "ee": 15.55,
      "he": 27.1247,
      "is": 0.8728,
      "as": 12.1959,
      "es": 4.47,
      "hs": 8.4459
    },
    {
      "Code": "BVS",
      "ib": 0,
      "ab": 2.2435,
      "eb": 0.77,
      "hb": 0.9837,
      "ie": -27.2542,
      "ae": 17.0693,
      "ee": 9.07,
      "he": 13.2455,
      "is": 0,
      "as": 12.2231,
      "es": 2.96,
      "hs": 2.6528
    },
    {
      "Code": "TVS",
      "ib": 0.7198,
      "ab": 2.8703,
      "eb": 1.05,
      "hb": 1.3105,
      "ie": 3.6945,
      "ae": 38.014,
      "ee": 7.63,
      "he": 13.9715,
      "is": 1.7063,
      "as": 4.8152,
      "es": 2.6,
      "hs": 3.2615
    },
    {
      "Code": "VDS",
      "ib": 0.4329,
      "ab": 2.4269,
      "eb": 0.85,
      "hb": 1.4667,
      "ie": -21.4433,
      "ae": 56.5738,
      "ee": 8.77,
      "he": 21.6304,
      "is": 0.8962,
      "as": 5.1509,
      "es": 2.19,
      "hs": 4.6943
    },
    {
      "Code": "ORS",
      "ib": 0.2433,
      "ab": 3.063,
      "eb": 0.98,
      "hb": 0.8844,
      "ie": -276.8825,
      "ae": 122.7011,
      "ee": 6.22,
      "he": 11.6592,
      "is": 0.5411,
      "as": 11.2195,
      "es": 3.2,
      "hs": 1.6928
    },
    {
      "Code": "SBS",
      "ib": -0.7566,
      "ab": 9.045,
      "eb": 1.41,
      "hb": 3.2409,
      "ie": -519.1337,
      "ae": 5596.7198,
      "ee": 11.45,
      "he": -9.7608,
      "is": 0.4413,
      "as": 12.465,
      "es": 3.15,
      "hs": 6.7511
    },
    {
      "Code": "APG",
      "ib": 0.3068,
      "ab": 1.8266,
      "eb": 0.72,
      "hb": 1.1176,
      "ie": -28.5285,
      "ae": 68.3131,
      "ee": 9.11,
      "he": -20.4329,
      "is": 1.687,
      "as": 20.6806,
      "es": 6.02,
      "hs": 23.6347
    },
    {
      "Code": "TVB",
      "ib": 0.3565,
      "ab": 2.6723,
      "eb": 0.99,
      "hb": 0.8684,
      "ie": -34.7917,
      "ae": 52.8451,
      "ee": 10.58,
      "he": 8.6235,
      "is": 1.9271,
      "as": 16.1828,
      "es": 6.41,
      "hs": 7.3786
    },
    {
      "Code": "PSI",
      "ib": 0.2127,
      "ab": 1.5884,
      "eb": 0.65,
      "hb": 0.6185,
      "ie": -48.532,
      "ae": 770.517,
      "ee": 20.48,
      "he": 18.5862,
      "is": 0.7698,
      "as": 5.2706,
      "es": 2.09,
      "hs": 1.278
    },
    {
      "Code": "IVS",
      "ib": 0.3926,
      "ab": 1.8272,
      "eb": 0.94,
      "hb": 0.8423,
      "ie": -13.8552,
      "ae": 2137.3023,
      "ee": 41.53,
      "he": 45.7772,
      "is": 1.2347,
      "as": 24.8614,
      "es": 9.44,
      "hs": 9.3367
    },
    {
      "Code": "VIG",
      "ib": 0.1411,
      "ab": 2.5733,
      "eb": 0.51,
      "hb": 0.8547,
      "ie": -109.3476,
      "ae": 586.9307,
      "ee": 8.93,
      "he": 37.5109,
      "is": 1.4211,
      "as": 40.8823,
      "es": 6.82,
      "hs": 8.9817
    },
    {
      "Code": "APS",
      "ib": 0,
      "ab": 2.6169,
      "eb": 0.46,
      "hb": 0.7467,
      "ie": -43.5906,
      "ae": 63.5619,
      "ee": 7.99,
      "he": -51.7177,
      "is": 0,
      "as": 11.0047,
      "es": 2.24,
      "hs": 2.4444
    },
    {
      "Code": "HAC",
      "ib": 0.3157,
      "ab": 2.0536,
      "eb": 0.61,
      "hb": 1.0919,
      "ie": -166.0097,
      "ae": 490.8026,
      "ee": 8.1,
      "he": -121.628,
      "is": 1.9322,
      "as": 11.9418,
      "es": 3.58,
      "hs": 6.5982
    },
    {
      "Code": "HBS",
      "ib": 0.1711,
      "ab": 1.4064,
      "eb": 0.47,
      "hb": 0.6414,
      "ie": 8.6266,
      "ae": 830.6741,
      "ee": 40.42,
      "he": 30.7222,
      "is": 4.889,
      "as": 25.4591,
      "es": 7.74,
      "hs": 8.7695
    },
    {
      "Code": "WSS",
      "ib": 0.1864,
      "ab": 1.9402,
      "eb": 0.5,
      "hb": 0.5378,
      "ie": -179.4809,
      "ae": 345.9886,
      "ee": 4.26,
      "he": -36.1561,
      "is": 1.0868,
      "as": 15.1499,
      "es": 6.01,
      "hs": 17.7429
    },
    {
      "Code": "DSC",
      "ib": 0.4479,
      "ab": 7.7904,
      "eb": 1.55,
      "hb": 1.3283,
      "ie": -719.1691,
      "ae": 1067.3104,
      "ee": 24.01,
      "he": 18.9723,
      "is": 1.5643,
      "as": 280.7857,
      "es": 8.6,
      "hs": 6.5099
    },
    {
      "Code": "EVS",
      "ib": 0.4553,
      "ab": 2.4957,
      "eb": 0.75,
      "hb": 0.5332,
      "ie": -49.0258,
      "ae": 137.729,
      "ee": 13.12,
      "he": 84.5532,
      "is": 1.0055,
      "as": 6.7526,
      "es": 3.25,
      "hs": 3.6706
    },
    {
      "Code": "TCI",
      "ib": 0.4187,
      "ab": 1.9405,
      "eb": 0.8,
      "hb": 0.8092,
      "ie": -9.8935,
      "ae": 25.2377,
      "ee": 11.83,
      "he": 17.5663,
      "is": 1.3639,
      "as": 11.8637,
      "es": 3.95,
      "hs": 4.1008
    },
    {
      "Code": "BMS",
      "ib": 0.2945,
      "ab": 1.7921,
      "eb": 0.71,
      "hb": 1.0984,
      "ie": -62.2435,
      "ae": 32.773,
      "ee": 6.5,
      "he": 17.1909,
      "is": 0.555,
      "as": 2.9846,
      "es": 1.22,
      "hs": 3.205
    },
    {
      "Code": "CSI",
      "ib": 1.22,
      "ab": 8.0876,
      "eb": 2.87,
      "hb": 3.3771,
      "ie": -196.3506,
      "ae": 620.5721,
      "ee": 36.79,
      "he": -34.6493,
      "is": 6.6806,
      "as": 67.8492,
      "es": 23.03,
      "hs": 31.8642
    },
    {
      "Code": "PHS",
      "ib": 0.769,
      "ab": 2.1327,
      "eb": 1.14,
      "hb": 1.0855,
      "ie": 12.6897,
      "ae": 15728.7159,
      "ee": 21.29,
      "he": 791.701,
      "is": 2.5611,
      "as": 7.6813,
      "es": 4.16,
      "hs": 4.2181
    },
    {
      "Code": "AAS",
      "ib": 0.5071,
      "ab": 2.5526,
      "eb": 0.81,
      "hb": 0.843,
      "ie": -326.7837,
      "ae": 85.9308,
      "ee": 10.71,
      "he": 32.3683,
      "is": 0.4678,
      "as": 5.3141,
      "es": 1.78,
      "hs": 5.4828
    }
  ],
  "ToJsonBH": [
    {
      "Code": "BVH",
      "ib": 1.4019,
      "ab": 4.7409,
      "eb": 2.43,
      "hb": 1.7222,
      "ie": 15.1813,
      "ae": 57.8055,
      "ee": 28.09,
      "he": 18.1494,
      "is": 0,
      "as": 8.2458,
      "es": 1.09,
      "hs": 0.9977
    },
    {
      "Code": "PVI",
      "ib": 0,
      "ab": 1.7038,
      "eb": 1,
      "hb": 1.6498,
      "ie": 0,
      "ae": 18.8934,
      "ee": 11.8,
      "he": 16.354,
      "is": 0,
      "as": 3.3134,
      "es": 1.28,
      "hs": 1.7195
    },
    {
      "Code": "VNR",
      "ib": 0,
      "ab": 1.4214,
      "eb": 0.96,
      "hb": 0.9987,
      "ie": 0,
      "ae": 13.608,
      "ee": 8.96,
      "he": 11.9363,
      "is": 0,
      "as": 4.754,
      "es": 1.95,
      "hs": 1.7911
    },
    {
      "Code": "BMI",
      "ib": 0.2742,
      "ab": 1.9114,
      "eb": 0.95,
      "hb": 0.9862,
      "ie": 3.8658,
      "ae": 19.2549,
      "ee": 11.5,
      "he": 12.3329,
      "is": 0,
      "as": 1.4662,
      "es": 0.54,
      "hs": 0.5419
    },
    {
      "Code": "PTI",
      "ib": 0.6569,
      "ab": 2.2659,
      "eb": 1.02,
      "hb": 1.1559,
      "ie": -28.3668,
      "ae": 68.8495,
      "ee": 10.1,
      "he": 8.7736,
      "is": 0,
      "as": 1.0204,
      "es": 0.4,
      "hs": 0.7727
    },
    {
      "Code": "BIC",
      "ib": 0.5863,
      "ab": 2.2701,
      "eb": 1.29,
      "hb": 1.4637,
      "ie": 5.1515,
      "ae": 34.9311,
      "ee": 10.17,
      "he": 8.3562,
      "is": 0,
      "as": 1.7843,
      "es": 1.04,
      "hs": 1.0538
    },
    {
      "Code": "PGI",
      "ib": 0.6459,
      "ab": 1.7878,
      "eb": 1.18,
      "hb": 1.2112,
      "ie": 3.7795,
      "ae": 15.5048,
      "ee": 10.41,
      "he": 9.5933,
      "is": 0,
      "as": 0.9957,
      "es": 0.41,
      "hs": 0.6619
    },
    {
      "Code": "ABI",
      "ib": 0.242,
      "ab": 2.0308,
      "eb": 1.16,
      "hb": 1.2838,
      "ie": 3.2882,
      "ae": 36.0592,
      "ee": 6.97,
      "he": 9.5887,
      "is": 0,
      "as": 1.5138,
      "es": 0.73,
      "hs": 0.9302
    },
    {
      "Code": "BLI",
      "ib": 0.5027,
      "ab": 1.4485,
      "eb": 0.67,
      "hb": 0.651,
      "ie": -49.8209,
      "ae": 514.8025,
      "ee": 10.57,
      "he": 9.6749,
      "is": 0,
      "as": 1.0291,
      "es": 0.47,
      "hs": 0.4833
    },
    {
      "Code": "MIG",
      "ib": 0.8449,
      "ab": 2.3011,
      "eb": 1.35,
      "hb": 1.4078,
      "ie": 8.5602,
      "ae": 28.3926,
      "ee": 13.11,
      "he": 11.9415,
      "is": 0,
      "as": 1.4592,
      "es": 0.76,
      "hs": 0.8267
    },
    {
      "Code": "PRE",
      "ib": 1.1188,
      "ab": 2.0793,
      "eb": 1.39,
      "hb": 1.2505,
      "ie": 6.0389,
      "ae": 11.6092,
      "ee": 9.3,
      "he": 10.6582,
      "is": 0.9374,
      "as": 1.9067,
      "es": 1.42,
      "hs": 1.458
    },
    {
      "Code": "AIC",
      "ib": 0.8049,
      "ab": 1.5725,
      "eb": 1.1,
      "hb": 0.9684,
      "ie": -358.2208,
      "ae": 136.1152,
      "ee": 54.26,
      "he": 90.0319,
      "is": 0.3908,
      "as": 1.3216,
      "es": 0.58,
      "hs": 0.4378
    }
  ],
  "ToJsonBDS": [
    {
      "Code": "VIC",
      "ib": 1.2105,
      "ab": 9.4617,
      "eb": 4.25,
      "hb": 2.7001,
      "ie": -123.8555,
      "ae": 113.2229,
      "ee": 42.26,
      "he": 35.9964,
      "is": 1.0067,
      "as": 41.4898,
      "es": 2.88,
      "hs": 1.5676
    },
    {
      "Code": "KDH",
      "ib": 0.3533,
      "ab": 3.1846,
      "eb": 1.74,
      "hb": 1.7808,
      "ie": -8.8995,
      "ae": 65.7359,
      "ee": 15.94,
      "he": 34.4119,
      "is": 1.5288,
      "as": 17.7492,
      "es": 4.51,
      "hs": 8.1827
    },
    {
      "Code": "PDR",
      "ib": 0.992,
      "ab": 7.4169,
      "eb": 1.94,
      "hb": 1.5682,
      "ie": 7.9138,
      "ae": 651.2823,
      "ee": 20.98,
      "he": 106.5263,
      "is": 2.1328,
      "as": 66.0318,
      "es": 8.52,
      "hs": 14.8621
    },
    {
      "Code": "DIG",
      "ib": 0.5762,
      "ab": 7.3723,
      "eb": 1.23,
      "hb": 1.5353,
      "ie": -636.8961,
      "ae": 446.1416,
      "ee": 29.51,
      "he": 60.7023,
      "is": 1.3851,
      "as": 18.9628,
      "es": 3.02,
      "hs": 9.3892
    },
    {
      "Code": "NLG",
      "ib": 1.0854,
      "ab": 2.3544,
      "eb": 1.49,
      "hb": 1.5542,
      "ie": 6.4877,
      "ae": 89.2337,
      "ee": 15.53,
      "he": 21.621,
      "is": 1.3794,
      "as": 6.8657,
      "es": 2.72,
      "hs": 1.8354
    },
    {
      "Code": "DXG",
      "ib": 0.6367,
      "ab": 4.4456,
      "eb": 1.27,
      "hb": 1.4436,
      "ie": -60.0585,
      "ae": 92.0036,
      "ee": 8.09,
      "he": 56.3686,
      "is": 0.7791,
      "as": 6.2019,
      "es": 1.92,
      "hs": 3.3054
    },
    {
      "Code": "CEO",
      "ib": 0.6165,
      "ab": 5.1195,
      "eb": 1.09,
      "hb": 1.676,
      "ie": -47.5104,
      "ae": 69.2192,
      "ee": 8.38,
      "he": 53.1062,
      "is": 0.488,
      "as": 14.8387,
      "es": 1.78,
      "hs": 7.6351
    },
    {
      "Code": "HDG",
      "ib": 0.7891,
      "ab": 5.1008,
      "eb": 1.82,
      "hb": 1.5145,
      "ie": 3.3269,
      "ae": 21.7581,
      "ee": 10.24,
      "he": 33.5819,
      "is": 0.4599,
      "as": 3.6983,
      "es": 1.25,
      "hs": 3.8369
    },
    {
      "Code": "SJS",
      "ib": 0.7823,
      "ab": 5.071,
      "eb": 1.49,
      "hb": 3.9645,
      "ie": -41.4348,
      "ae": 224.0915,
      "ee": 22.95,
      "he": 41.393,
      "is": -117.4801,
      "as": 45.3846,
      "es": 5.24,
      "hs": 17.9905
    },
    {
      "Code": "IJC",
      "ib": 0.6228,
      "ab": 2.2526,
      "eb": 0.94,
      "hb": 0.9304,
      "ie": 4.3522,
      "ae": 24.7519,
      "ee": 9.81,
      "he": 11.1708,
      "is": 0.6272,
      "as": 8.7859,
      "es": 2.45,
      "hs": 3.9947
    },
    {
      "Code": "HDC",
      "ib": 0.6739,
      "ab": 5.5976,
      "eb": 1.14,
      "hb": 2.0798,
      "ie": 4.5241,
      "ae": 52.9939,
      "ee": 10.7,
      "he": 59.658,
      "is": 0.9838,
      "as": 7.5937,
      "es": 1.61,
      "hs": 8.3455
    },
    {
      "Code": "VC3",
      "ib": 0,
      "ab": 4.546,
      "eb": 1.65,
      "hb": 2.5625,
      "ie": 0,
      "ae": 153.0746,
      "ee": 14.95,
      "he": 56.729,
      "is": 0,
      "as": 24.5245,
      "es": 1.4,
      "hs": 5.618
    },
    {
      "Code": "SCR",
      "ib": 0.3017,
      "ab": 1.4022,
      "eb": 0.59,
      "hb": 0.6204,
      "ie": -527.3964,
      "ae": 351.9355,
      "ee": 13.07,
      "he": -6691.7363,
      "is": 0.8699,
      "as": 13.937,
      "es": 2.38,
      "hs": 3.6627
    },
    {
      "Code": "QCG",
      "ib": 0.2661,
      "ab": 1.541,
      "eb": 0.52,
      "hb": 0.8207,
      "ie": -206.2363,
      "ae": 245.4442,
      "ee": 26.02,
      "he": 37.8244,
      "is": 0.5779,
      "as": 10.1105,
      "es": 2.71,
      "hs": 4.3058
    },
    {
      "Code": "HQC",
      "ib": 0.1192,
      "ab": 1.9866,
      "eb": 0.41,
      "hb": 0.3977,
      "ie": 0.778,
      "ae": 735.3498,
      "ee": 17.5,
      "he": 63.5534,
      "is": 0.2123,
      "as": 17.7594,
      "es": 1.78,
      "hs": -68.9133
    },
    {
      "Code": "TIG",
      "ib": 0.2617,
      "ab": 2.1384,
      "eb": 0.67,
      "hb": 0.7236,
      "ie": -8.9775,
      "ae": 30.0604,
      "ee": 7.28,
      "he": 8.8902,
      "is": 0.8588,
      "as": 12.53,
      "es": 1.86,
      "hs": 0.9996
    },
    {
      "Code": "NBB",
      "ib": 0.283,
      "ab": 2.3861,
      "eb": 0.99,
      "hb": 1.2129,
      "ie": 2.039,
      "ae": 1873.5594,
      "ee": 13.96,
      "he": 2338.3338,
      "is": 0.6104,
      "as": 37.2067,
      "es": 3.35,
      "hs": 43.4012
    },
    {
      "Code": "NTL",
      "ib": 0.618,
      "ab": 5.4437,
      "eb": 1.17,
      "hb": 1.3759,
      "ie": 2.3054,
      "ae": 77.0904,
      "ee": 7.39,
      "he": 3.9078,
      "is": 0.9035,
      "as": 4.4695,
      "es": 1.84,
      "hs": 1.724
    },
    {
      "Code": "D2D",
      "ib": 0.5321,
      "ab": 2.7908,
      "eb": 1.12,
      "hb": 1.4206,
      "ie": 2.2633,
      "ae": 68.341,
      "ee": 7.05,
      "he": 11.2275,
      "is": 0.6174,
      "as": 6.7017,
      "es": 2.1,
      "hs": 2.6
    },
    {
      "Code": "IDJ",
      "ib": 0.2323,
      "ab": 2.9018,
      "eb": 0.46,
      "hb": 0.4267,
      "ie": -103.1682,
      "ae": 303.0377,
      "ee": 5.23,
      "he": 9.5313,
      "is": 0.301,
      "as": 6.9243,
      "es": 2.07,
      "hs": 1.1722
    },
    {
      "Code": "ITC",
      "ib": 0.2689,
      "ab": 1.566,
      "eb": 0.52,
      "hb": 0.65,
      "ie": -32.4755,
      "ae": 102.8101,
      "ee": 12.32,
      "he": 43.3316,
      "is": 0.8691,
      "as": 4.9539,
      "es": 1.86,
      "hs": 2.3894
    },
    {
      "Code": "TDC",
      "ib": 0.5414,
      "ab": 2.6261,
      "eb": 0.82,
      "hb": 1.2048,
      "ie": -2.5665,
      "ae": 177.1969,
      "ee": 6.18,
      "he": 2.5857,
      "is": 0.3564,
      "as": 2.0856,
      "es": 0.59,
      "hs": 1.0048
    },
    {
      "Code": "CSC",
      "ib": 0.2735,
      "ab": 6.8024,
      "eb": 1.47,
      "hb": 1.4348,
      "ie": -94.9012,
      "ae": 113.4291,
      "ee": 14.29,
      "he": 62.4053,
      "is": 0.1182,
      "as": 7.3781,
      "es": 0.66,
      "hs": 1.4135
    },
    {
      "Code": "NDN",
      "ib": 0.4711,
      "ab": 1.6134,
      "eb": 0.81,
      "hb": 0.651,
      "ie": -4.7465,
      "ae": 18.6221,
      "ee": 5.74,
      "he": 15.1836,
      "is": 0.4318,
      "as": 20.7055,
      "es": 1.76,
      "hs": 16.0177
    },
    {
      "Code": "VPH",
      "ib": 0.2216,
      "ab": 4.8317,
      "eb": 0.58,
      "hb": 0.4969,
      "ie": -165.6574,
      "ae": 180.4492,
      "ee": 10.28,
      "he": 3.9807,
      "is": 0.4746,
      "as": 13.2472,
      "es": 1.55,
      "hs": 10.7943
    },
    {
      "Code": "DRH",
      "ib": 0.1656,
      "ab": 2.777,
      "eb": 0.53,
      "hb": 0.3408,
      "ie": -121.6253,
      "ae": 109.9404,
      "ee": 10.83,
      "he": -1.6281,
      "is": 0.1719,
      "as": 88.3613,
      "es": 5.77,
      "hs": 125.118
    },
    {
      "Code": "HLD",
      "ib": 0.4948,
      "ab": 2.0464,
      "eb": 0.9,
      "hb": 1.9362,
      "ie": 2.6977,
      "ae": 200.8435,
      "ee": 5.88,
      "he": 103.8053,
      "is": 0.459,
      "as": 37.7707,
      "es": 1.19,
      "hs": 15.229
    },
    {
      "Code": "VRC",
      "ib": 0.3206,
      "ab": 2.4895,
      "eb": 0.57,
      "hb": 0.6413,
      "ie": -171.1901,
      "ae": 2284.9994,
      "ee": 25.89,
      "he": 59.0105,
      "is": 0.4243,
      "as": 277.9,
      "es": 18.74,
      "hs": 73.5393
    },
    {
      "Code": "CCL",
      "ib": 0.2607,
      "ab": 1.3129,
      "eb": 0.51,
      "hb": 0.6109,
      "ie": 4.6594,
      "ae": 69.4558,
      "ee": 10.46,
      "he": 10.1702,
      "is": 0.4693,
      "as": 3.8708,
      "es": 1.5,
      "hs": 1.5104
    },
    {
      "Code": "TDH",
      "ib": 0.3204,
      "ab": 3.7265,
      "eb": 0.57,
      "hb": 6.5133,
      "ie": -43.9452,
      "ae": 75.1066,
      "ee": 6.79,
      "he": -1.6653,
      "is": 0.2168,
      "as": 6.8149,
      "es": 1.22,
      "hs": 10.5793
    },
    {
      "Code": "HAR",
      "ib": 0.261,
      "ab": 2.1205,
      "eb": 0.46,
      "hb": 0.3479,
      "ie": -66.2641,
      "ae": 766.9245,
      "ee": 22.97,
      "he": 27.1777,
      "is": 1.8715,
      "as": 43.658,
      "es": 6.62,
      "hs": 21.3811
    },
    {
      "Code": "PTL",
      "ib": 0.2025,
      "ab": 1.6295,
      "eb": 0.48,
      "hb": 0.706,
      "ie": -186.4572,
      "ae": 385.0829,
      "ee": 5,
      "he": -5.988,
      "is": 0.3442,
      "as": 208.3752,
      "es": 3.35,
      "hs": 0.8781
    },
    {
      "Code": "PFL",
      "ib": 0.1118,
      "ab": 1.7883,
      "eb": 0.35,
      "hb": 0.5355,
      "ie": -60.6656,
      "ae": 318.6619,
      "ee": -2.33,
      "he": 35.1238,
      "is": 0.409,
      "as": 60.7348,
      "es": 3.25,
      "hs": 0.9675
    },
    {
      "Code": "LDG",
      "ib": 0.2113,
      "ab": 1.9237,
      "eb": 0.65,
      "hb": 1.0092,
      "ie": -9.1998,
      "ae": 260.1932,
      "ee": 5.2,
      "he": -0.9038,
      "is": -4.5,
      "as": 20.308,
      "es": 2.16,
      "hs": 36.2807
    },
    {
      "Code": "API",
      "ib": 0.2767,
      "ab": 3.1981,
      "eb": 0.91,
      "hb": 0.7187,
      "ie": -32.9176,
      "ae": 352.8125,
      "ee": 7.47,
      "he": -36.1945,
      "is": 0,
      "as": 96.9555,
      "es": 1.17,
      "hs": 2.6652
    },
    {
      "Code": "NVL",
      "ib": 0.5354,
      "ab": 4.8574,
      "eb": 2.8,
      "hb": 0.7964,
      "ie": -56.0005,
      "ae": 52.5728,
      "ee": 21.76,
      "he": -4.7589,
      "is": 2.1318,
      "as": 17.7786,
      "es": 5.27,
      "hs": 2.9671
    },
    {
      "Code": "SGR",
      "ib": 0.7288,
      "ab": 2.9163,
      "eb": 1.49,
      "hb": 2.2536,
      "ie": -217.3419,
      "ae": 47.6379,
      "ee": 8.39,
      "he": 16.4865,
      "is": 0.9823,
      "as": 38.9455,
      "es": 2.78,
      "hs": 12.3713
    },
    {
      "Code": "TEG",
      "ib": 0.3811,
      "ab": 1.8943,
      "eb": 0.74,
      "hb": 0.5795,
      "ie": -109.2109,
      "ae": 173.8959,
      "ee": 10.78,
      "he": 132.5173,
      "is": 0.6525,
      "as": 8.857,
      "es": 1.78,
      "hs": 2.5664
    },
    {
      "Code": "VRE",
      "ib": 0.9594,
      "ab": 4.0211,
      "eb": 2.21,
      "hb": 1.4999,
      "ie": 9.4422,
      "ae": 68.0023,
      "ee": 27.56,
      "he": 15.4268,
      "is": 4.148,
      "as": 17.0532,
      "es": 8.17,
      "hs": 7.3331
    },
    {
      "Code": "VPI",
      "ib": 2.5315,
      "ab": 4.6899,
      "eb": 3.51,
      "hb": 3.4057,
      "ie": 9.5388,
      "ae": 84.2439,
      "ee": 22.91,
      "he": 42.684,
      "is": 2.0519,
      "as": 26.9261,
      "es": 6.21,
      "hs": 7.9731
    },
    {
      "Code": "KOS",
      "ib": 1.6534,
      "ab": 3.931,
      "eb": 3.24,
      "hb": 3.6067,
      "ie": 28.1651,
      "ae": 542.6356,
      "ee": 157.71,
      "he": 394.2036,
      "is": 1.9117,
      "as": 6.9586,
      "es": 3.97,
      "hs": 5.8428
    },
    {
      "Code": "TLD",
      "ib": 0.298,
      "ab": 1.426,
      "eb": 0.56,
      "hb": 0.6775,
      "ie": 4.8276,
      "ae": 78.7068,
      "ee": 13.19,
      "he": 39.1185,
      "is": 0.2169,
      "as": 1.7642,
      "es": 0.74,
      "hs": 0.9413
    },
    {
      "Code": "AAV",
      "ib": 0.3503,
      "ab": 2.5555,
      "eb": 0.72,
      "hb": 0.6257,
      "ie": -199.7331,
      "ae": 182.9944,
      "ee": 6.7,
      "he": -36.934,
      "is": 0.2909,
      "as": 68.5863,
      "es": 1.13,
      "hs": 4.684
    },
    {
      "Code": "VHM",
      "ib": 0.8562,
      "ab": 8.2529,
      "eb": 3.19,
      "hb": 1.7204,
      "ie": 3.0228,
      "ae": 8345.338,
      "ee": 10.85,
      "he": 11.074,
      "is": 0.5349,
      "as": 4080,
      "es": 3.96,
      "hs": 3.389
    },
    {
      "Code": "CRE",
      "ib": 0.5661,
      "ab": 3.8255,
      "eb": 1.12,
      "hb": 0.7373,
      "ie": -122.1472,
      "ae": 1604.4212,
      "ee": 8.19,
      "he": 117.4373,
      "is": 0.5672,
      "as": 4.734,
      "es": 1.28,
      "hs": 3.4582
    },
    {
      "Code": "HTN",
      "ib": 0.4848,
      "ab": 2.8889,
      "eb": 0.96,
      "hb": 0.5866,
      "ie": -95.9268,
      "ae": 49.0095,
      "ee": 5.05,
      "he": 21.3517,
      "is": 0.1395,
      "as": 0.915,
      "es": 0.36,
      "hs": 0.9973
    },
    {
      "Code": "FIR",
      "ib": 0.5103,
      "ab": 3.2752,
      "eb": 1.93,
      "hb": 0.7768,
      "ie": -185.8766,
      "ae": 190.6624,
      "ee": 14.58,
      "he": -185.8766,
      "is": 1.6092,
      "as": 7.1401,
      "es": 4.26,
      "hs": 6.5942
    },
    {
      "Code": "NRC",
      "ib": 0.2893,
      "ab": 3.5549,
      "eb": 0.93,
      "hb": 0.5141,
      "ie": -78.4752,
      "ae": 53.2063,
      "ee": 5.92,
      "he": -3.7237,
      "is": 0.4301,
      "as": 112.8444,
      "es": 3.76,
      "hs": 77.4968
    },
    {
      "Code": "AGG",
      "ib": 0.8077,
      "ab": 2.4973,
      "eb": 1.57,
      "hb": 0.8816,
      "ie": -182.2192,
      "ae": 185.6407,
      "ee": 8.53,
      "he": 24.9539,
      "is": 0.3331,
      "as": 11.5171,
      "es": 1.47,
      "hs": 3.3847
    },
    {
      "Code": "CKG",
      "ib": 0.7597,
      "ab": 2.9569,
      "eb": 1.63,
      "hb": 1.5578,
      "ie": 4.1011,
      "ae": 24.1417,
      "ee": 12.88,
      "he": 14.6718,
      "is": 0.3871,
      "as": 3.5713,
      "es": 1.48,
      "hs": 1.4951
    }
  ],
  "ToJsonBDSKCN": [
    {
      "Code": "CCI",
      "ib": 0.5981,
      "ab": 2.1042,
      "eb": 0.93,
      "hb": 1.5809,
      "ie": 3.3227,
      "ae": 27.4509,
      "ee": 8.78,
      "he": 11.0556,
      "is": 0.2811,
      "as": 1.7036,
      "es": 0.67,
      "hs": 0.9825
    },
    {
      "Code": "DPR",
      "ib": 0.5793,
      "ab": 3.0857,
      "eb": 1,
      "hb": 1.3927,
      "ie": 2.8121,
      "ae": 16.7998,
      "ee": 7.93,
      "he": 12.8365,
      "is": 1.2718,
      "as": 3.9487,
      "es": 1.73,
      "hs": 2.8472
    },
    {
      "Code": "IDV",
      "ib": 1.1566,
      "ab": 3.6289,
      "eb": 2.13,
      "hb": 1.2538,
      "ie": 3.8861,
      "ae": 18.9772,
      "ee": 6.65,
      "he": 8.8155,
      "is": 1.9156,
      "as": 13.1305,
      "es": 5.18,
      "hs": 10.3931
    },
    {
      "Code": "ITA",
      "ib": 0.2121,
      "ab": 1.6075,
      "eb": 0.51,
      "hb": 0.2121,
      "ie": -24.4699,
      "ae": 209.1237,
      "ee": 26.84,
      "he": 10.0245,
      "is": 1.7275,
      "as": 453.4404,
      "es": 6.84,
      "hs": 5.742
    },
    {
      "Code": "KBC",
      "ib": 0.4981,
      "ab": 3.2243,
      "eb": 0.97,
      "hb": 1.3342,
      "ie": -9.5142,
      "ae": 104.622,
      "ee": 11.64,
      "he": 16.9991,
      "is": 2.0606,
      "as": 14.2437,
      "es": 5.24,
      "hs": 3.7027
    },
    {
      "Code": "LGL",
      "ib": 0.1859,
      "ab": 2.6141,
      "eb": 0.47,
      "hb": 0.3256,
      "ie": -46.036,
      "ae": 179.423,
      "ee": 5.85,
      "he": -4.989,
      "is": 0.2339,
      "as": 3.8576,
      "es": 1.15,
      "hs": 2.057
    },
    {
      "Code": "LHG",
      "ib": 0.3869,
      "ab": 2.3085,
      "eb": 0.85,
      "hb": 0.9337,
      "ie": -10.3759,
      "ae": 14.6029,
      "ee": 6.11,
      "he": 6.2215,
      "is": 0.8819,
      "as": 4.433,
      "es": 1.77,
      "hs": 2.8493
    },
    {
      "Code": "PHR",
      "ib": 0.6424,
      "ab": 3.6633,
      "eb": 1.67,
      "hb": 2.1493,
      "ie": 2.7706,
      "ae": 19.3872,
      "ee": 7.88,
      "he": 17.2694,
      "is": 0.8578,
      "as": 6.1311,
      "es": 2.22,
      "hs": 5.1401
    },
    {
      "Code": "SZL",
      "ib": 0.4576,
      "ab": 2.376,
      "eb": 1.25,
      "hb": 1.8055,
      "ie": 4.0193,
      "ae": 17.7499,
      "ee": 7.84,
      "he": 10.9932,
      "is": 1.4923,
      "as": 9.7642,
      "es": 2.22,
      "hs": 2.3799
    },
    {
      "Code": "TIX",
      "ib": 0.7302,
      "ab": 1.6282,
      "eb": 1.18,
      "hb": 1.3686,
      "ie": 3.5106,
      "ae": 13.5797,
      "ee": 8.18,
      "he": 10.6777,
      "is": 0.3813,
      "as": 5.3327,
      "es": 3.43,
      "hs": 5.1357
    },
    {
      "Code": "PXL",
      "ib": 0.19,
      "ab": 1.6231,
      "eb": 0.48,
      "hb": 1.263,
      "ie": -99.1609,
      "ae": 2029.0304,
      "ee": 46.7,
      "he": 1697.3451,
      "is": 0.999,
      "as": 393.9196,
      "es": 58.27,
      "hs": 127.3841
    },
    {
      "Code": "BII",
      "ib": 0.067,
      "ab": 2.0617,
      "eb": 0.22,
      "hb": 0.0894,
      "ie": -49.572,
      "ae": 209.0756,
      "ee": 11.39,
      "he": -3.427,
      "is": 0,
      "as": 21.4559,
      "es": 1.49,
      "hs": 0
    },
    {
      "Code": "TIP",
      "ib": 0.6583,
      "ab": 2.3252,
      "eb": 1,
      "hb": 0.7019,
      "ie": 4.451,
      "ae": 17.3476,
      "ee": 7.4,
      "he": 7.2096,
      "is": 1.9481,
      "as": 10.5653,
      "es": 3.33,
      "hs": 7.7151
    },
    {
      "Code": "VGC",
      "ib": 0.8317,
      "ab": 3.5593,
      "eb": 1.78,
      "hb": 2.3888,
      "ie": 7.451,
      "ae": 30.8571,
      "ee": 14.53,
      "he": 16.8409,
      "is": 0.2708,
      "as": 2.2309,
      "es": 1.12,
      "hs": 1.694
    },
    {
      "Code": "VRG",
      "ib": 0.2515,
      "ab": 3.1073,
      "eb": 1.1,
      "hb": 1.5475,
      "ie": -49.2942,
      "ae": 326.0838,
      "ee": 18.52,
      "he": 10.5253,
      "is": 1.1403,
      "as": 47.1955,
      "es": 10.67,
      "hs": 5.3165
    },
    {
      "Code": "BAX",
      "ib": 1.191,
      "ab": 3.2077,
      "eb": 1.88,
      "hb": 1.3475,
      "ie": 3.6262,
      "ae": 24.7533,
      "ee": 8.03,
      "he": 10.8253,
      "is": 1.7116,
      "as": 5.8812,
      "es": 2.97,
      "hs": 3.8604
    },
    {
      "Code": "MH3",
      "ib": 1.1261,
      "ab": 4.2634,
      "eb": 1.76,
      "hb": 1.3586,
      "ie": 3.8645,
      "ae": 18.6037,
      "ee": 10.72,
      "he": 16.8961,
      "is": 2.4638,
      "as": 15.7583,
      "es": 6.24,
      "hs": 8.1242
    },
    {
      "Code": "NTC",
      "ib": 2.3494,
      "ab": 8.7161,
      "eb": 4.39,
      "hb": 3.4057,
      "ie": 3.8977,
      "ae": 20.8655,
      "ee": 12.52,
      "he": 13.5532,
      "is": 3.405,
      "as": 23.4149,
      "es": 13.7,
      "hs": 9.0238
    },
    {
      "Code": "BCM",
      "ib": 0.0549,
      "ab": 5.2973,
      "eb": 3.46,
      "hb": 3.5594,
      "ie": 8.021,
      "ae": 154.073,
      "ee": 25.96,
      "he": 29.2517,
      "is": 0.0701,
      "as": 15.9779,
      "es": 7.71,
      "hs": 11.3237
    },
    {
      "Code": "DTD",
      "ib": 0.7179,
      "ab": 2.5208,
      "eb": 1.25,
      "hb": 1.025,
      "ie": 2.872,
      "ae": 21.9643,
      "ee": 7.58,
      "he": 8.5539,
      "is": 0.6069,
      "as": 3.1401,
      "es": 1.22,
      "hs": 2.2798
    },
    {
      "Code": "HPI",
      "ib": 0.6379,
      "ab": 10.9053,
      "eb": 2.85,
      "hb": 3.1821,
      "ie": 4.4913,
      "ae": 56.0286,
      "ee": 11.38,
      "he": 23.2689,
      "is": -48.2562,
      "as": 46.4746,
      "es": 3.17,
      "hs": 35.1174
    },
    {
      "Code": "SNZ",
      "ib": 0.8896,
      "ab": 3.4085,
      "eb": 1.78,
      "hb": 1.6943,
      "ie": 9.414,
      "ae": 23.6534,
      "ee": 13.92,
      "he": 11.3593,
      "is": 0.9831,
      "as": 3.7732,
      "es": 1.99,
      "hs": 1.9074
    },
    {
      "Code": "GVR",
      "ib": 0.5307,
      "ab": 3.127,
      "eb": 1.62,
      "hb": 2.217,
      "ie": 8.5514,
      "ae": 53.5349,
      "ee": 22.08,
      "he": 25.629,
      "is": 0.0683,
      "as": 6.2542,
      "es": 3.41,
      "hs": 4.4048
    },
    {
      "Code": "IDC",
      "ib": 0.3552,
      "ab": 5.7125,
      "eb": 2.63,
      "hb": 2.8144,
      "ie": 2.5366,
      "ae": 46.6044,
      "ee": 12.22,
      "he": 9.3529,
      "is": 0.3043,
      "as": 5.1889,
      "es": 1.79,
      "hs": 1.8816
    },
    {
      "Code": "SZC",
      "ib": 1.1414,
      "ab": 5.0696,
      "eb": 2.38,
      "hb": 2.0466,
      "ie": 10.4005,
      "ae": 27.1838,
      "ee": 18.34,
      "he": 18.046,
      "is": 3.1552,
      "as": 10.609,
      "es": 6.03,
      "hs": 6.1227
    },
    {
      "Code": "TID",
      "ib": 1.5406,
      "ab": 5.4647,
      "eb": 2.28,
      "hb": 1.5991,
      "ie": -160.56,
      "ae": 99.5831,
      "ee": 29.13,
      "he": 8.1116,
      "is": 0.3358,
      "as": 1.6819,
      "es": 0.53,
      "hs": 0.3516
    },
    {
      "Code": "TLP",
      "ib": 0.5772,
      "ab": 1.4003,
      "eb": 0.88,
      "hb": 0.6659,
      "ie": -346.314,
      "ae": 75.4526,
      "ee": 15.34,
      "he": 36.1745,
      "is": 0.0236,
      "as": 0.3862,
      "es": 0.15,
      "hs": 0.0816
    },
    {
      "Code": "SIP",
      "ib": 1.8961,
      "ab": 7.1244,
      "eb": 3.93,
      "hb": 3.1864,
      "ie": 7.6656,
      "ae": 33.316,
      "ee": 13.18,
      "he": 11.6849,
      "is": 1.0489,
      "as": 3.169,
      "es": 2.04,
      "hs": 1.8829
    },
    {
      "Code": "SZB",
      "ib": 1.368,
      "ab": 2.1575,
      "eb": 1.75,
      "hb": 1.754,
      "ie": 6.0967,
      "ae": 11.8843,
      "ee": 8.6,
      "he": 10.0436,
      "is": 2.2474,
      "as": 3.6498,
      "es": 2.64,
      "hs": 2.9298
    },
    {
      "Code": "SZG",
      "ib": 2.0166,
      "ab": 3.2136,
      "eb": 2.41,
      "hb": 2.0073,
      "ie": 8.8488,
      "ae": 35.4801,
      "ee": 12.17,
      "he": 9.4704,
      "is": 3.8446,
      "as": 6.4795,
      "es": 4.68,
      "hs": 4.2503
    }
  ],
  "ToJsonDauKhi": [
    {
      "Code": "PVD",
      "ib": 0.3281,
      "ab": 4.5981,
      "eb": 0.92,
      "hb": 0.7184,
      "ie": -215.9997,
      "ae": 2803.28,
      "ee": 12.8,
      "he": 16.6171,
      "is": 0.627,
      "as": 3.3344,
      "es": 1.43,
      "hs": 1.2741
    },
    {
      "Code": "PVS",
      "ib": 0,
      "ab": 2.5481,
      "eb": 0.94,
      "hb": 1.1555,
      "ie": 0,
      "ae": 23.3596,
      "ee": 8.62,
      "he": 14.5914,
      "is": 0,
      "as": 1.0446,
      "es": 0.45,
      "hs": 0.6159
    },
    {
      "Code": "POS",
      "ib": 0.4074,
      "ab": 1.2468,
      "eb": 0.63,
      "hb": 0.9327,
      "ie": 4.7494,
      "ae": 27.9789,
      "ee": 10.86,
      "he": 10.2795,
      "is": 0.1506,
      "as": 0.4834,
      "es": 0.3,
      "hs": 0.3653
    },
    {
      "Code": "PXS",
      "ib": 0.4554,
      "ab": 2.863,
      "eb": 0.97,
      "hb": 1.4741,
      "ie": -24.6514,
      "ae": 169.9364,
      "ee": 3.79,
      "he": 15.6193,
      "is": 0.2632,
      "as": 1.9598,
      "es": 0.47,
      "hs": 0.3023
    },
    {
      "Code": "PXT",
      "ib": 0.27,
      "ab": 4.0789,
      "eb": 0.91,
      "hb": 0.57,
      "ie": -23.8506,
      "ae": 133.3811,
      "ee": 3.11,
      "he": 22.2275,
      "is": 0.0982,
      "as": 2.6864,
      "es": 0.33,
      "hs": 0.3298
    },
    {
      "Code": "PVB",
      "ib": 0.6212,
      "ab": 2.8425,
      "eb": 1.01,
      "hb": 1.7132,
      "ie": -58.6392,
      "ae": 209.4731,
      "ee": 5.21,
      "he": -336.3941,
      "is": 0.3539,
      "as": 19.8557,
      "es": 2.18,
      "hs": 2.6696
    },
    {
      "Code": "PVC",
      "ib": 0,
      "ab": 2.4065,
      "eb": 0.87,
      "hb": 1.0331,
      "ie": -32.2436,
      "ae": 161.0891,
      "ee": 9.31,
      "he": 163.3284,
      "is": 0,
      "as": 1.2163,
      "es": 0.22,
      "hs": 0.272
    },
    {
      "Code": "GAS",
      "ib": 2.0084,
      "ab": 5.8603,
      "eb": 3.34,
      "hb": 2.5433,
      "ie": 6.7245,
      "ae": 25.6451,
      "ee": 15.09,
      "he": 15.0554,
      "is": 1.133,
      "as": 3.3003,
      "es": 2.02,
      "hs": 1.5128
    },
    {
      "Code": "PVT",
      "ib": 0.3791,
      "ab": 2.1535,
      "eb": 1.13,
      "hb": 1.0809,
      "ie": 4.7708,
      "ae": 179.8366,
      "ee": 9.6,
      "he": 7.9604,
      "is": 0.219,
      "as": 1.7441,
      "es": 0.65,
      "hs": 0.7159
    },
    {
      "Code": "PJT",
      "ib": 0.4787,
      "ab": 1.211,
      "eb": 0.8,
      "hb": 0.7626,
      "ie": -54.4273,
      "ae": 19.334,
      "ee": 5.72,
      "he": 9.6736,
      "is": 0.1365,
      "as": 0.4685,
      "es": 0.28,
      "hs": 0.3715
    },
    {
      "Code": "PVP",
      "ib": 0.3872,
      "ab": 1.2662,
      "eb": 0.73,
      "hb": 0.8603,
      "ie": 2.9739,
      "ae": 15.1475,
      "ee": 6.51,
      "he": 8.0951,
      "is": 0.3064,
      "as": 1.3486,
      "es": 0.75,
      "hs": 0.8837
    },
    {
      "Code": "PDV",
      "ib": 0.2684,
      "ab": 1.2524,
      "eb": 0.66,
      "hb": 0.9012,
      "ie": -105.6617,
      "ae": 78.0057,
      "ee": 9.13,
      "he": 3.5855,
      "is": 0.0864,
      "as": 0.5546,
      "es": 0.24,
      "hs": 0.5449
    },
    {
      "Code": "PLC",
      "ib": 0,
      "ab": 2.6996,
      "eb": 1.43,
      "hb": 1.6142,
      "ie": 0,
      "ae": 35.5863,
      "ee": 8.35,
      "he": 34.8427,
      "is": 0,
      "as": 0.5076,
      "es": 0.25,
      "hs": 0.2855
    },
    {
      "Code": "BSR",
      "ib": 0.6208,
      "ab": 2.3002,
      "eb": 1.2,
      "hb": 1.0399,
      "ie": -470.6395,
      "ae": 97.173,
      "ee": 8.22,
      "he": -510.0861,
      "is": 0.1845,
      "as": 0.947,
      "es": 0.44,
      "hs": 0.468
    },
    {
      "Code": "PLX",
      "ib": 1.658,
      "ab": 5.1755,
      "eb": 2.83,
      "hb": 1.8417,
      "ie": 12.759,
      "ae": 71.6092,
      "ee": 18.88,
      "he": 24.692,
      "is": 0.1476,
      "as": 0.6172,
      "es": 0.35,
      "hs": 0.174
    },
    {
      "Code": "OIL",
      "ib": 0.7476,
      "ab": 2.1261,
      "eb": 1.21,
      "hb": 1.1358,
      "ie": -98.4843,
      "ae": 81.1474,
      "ee": 29.76,
      "he": 57.9431,
      "is": 0.0808,
      "as": 0.3815,
      "es": 0.13,
      "hs": 0.0934
    },
    {
      "Code": "PPY",
      "ib": 0.514,
      "ab": 1.6706,
      "eb": 1.02,
      "hb": 0.542,
      "ie": 2.6989,
      "ae": 28.942,
      "ee": 7.91,
      "he": 9.97,
      "is": 0.0174,
      "as": 0.1086,
      "es": 0.07,
      "hs": 0.0203
    },
    {
      "Code": "PSH",
      "ib": 0.2983,
      "ab": 2.0624,
      "eb": 0.85,
      "hb": 0.38,
      "ie": -104.3071,
      "ae": 90.8215,
      "ee": 4.44,
      "he": -0.2461,
      "is": 0.0919,
      "as": 1.025,
      "es": 0.26,
      "hs": 1.025
    },
    {
      "Code": "PGC",
      "ib": 0.3803,
      "ab": 1.6715,
      "eb": 1.07,
      "hb": 0.9389,
      "ie": 5.257,
      "ae": 98.9022,
      "ee": 8.15,
      "he": 7.8546,
      "is": 0.0828,
      "as": 0.4526,
      "es": 0.25,
      "hs": 0.19
    },
    {
      "Code": "PGD",
      "ib": 1.214,
      "ab": 3.3842,
      "eb": 2.05,
      "hb": 1.6774,
      "ie": 3.1597,
      "ae": 27.6454,
      "ee": 10.99,
      "he": 11.652,
      "is": 0.2125,
      "as": 1.3016,
      "es": 0.37,
      "hs": 0.2209
    },
    {
      "Code": "PGS",
      "ib": 0,
      "ab": 2.8131,
      "eb": 1.2,
      "hb": 1.7968,
      "ie": 0,
      "ae": 28.6029,
      "ee": 9.8,
      "he": 16.0656,
      "is": 0,
      "as": 0.2865,
      "es": 0.18,
      "hs": 0.2875
    },
    {
      "Code": "PVG",
      "ib": 0.4734,
      "ab": 2.1397,
      "eb": 0.64,
      "hb": 0.545,
      "ie": -233.719,
      "ae": 649.6423,
      "ee": 16.35,
      "he": 18.5698,
      "is": 0.0453,
      "as": 0.4757,
      "es": 0.08,
      "hs": 0.0481
    },
    {
      "Code": "CNG",
      "ib": 1.0795,
      "ab": 2.7783,
      "eb": 1.71,
      "hb": 1.6292,
      "ie": 3.5817,
      "ae": 13.9937,
      "ee": 7.71,
      "he": 11.3214,
      "is": 0.1777,
      "as": 1.2366,
      "es": 0.48,
      "hs": 0.2757
    }
  ],
  "ToJsonDuoc": [
    {
      "Code": "DCL",
      "ib": 0.4285,
      "ab": 2.4431,
      "eb": 1.29,
      "hb": 1.1083,
      "ie": -17.3134,
      "ae": 166.3581,
      "ee": 13.41,
      "he": 29.6341,
      "is": 0.1535,
      "as": 3.3999,
      "es": 1.31,
      "hs": 1.2219
    },
    {
      "Code": "DHG",
      "ib": 2.4367,
      "ab": 5.0447,
      "eb": 3.32,
      "hb": 3.0401,
      "ie": 7.8607,
      "ae": 22.5884,
      "ee": 14.55,
      "he": 16.1679,
      "is": 1.4988,
      "as": 3.926,
      "es": 2.59,
      "hs": 2.75
    },
    {
      "Code": "DMC",
      "ib": 0.7245,
      "ab": 4.2035,
      "eb": 1.5,
      "hb": 1.3036,
      "ie": 4.4353,
      "ae": 20.7475,
      "ee": 10.36,
      "he": 10.3629,
      "is": 0.3659,
      "as": 2.9975,
      "es": 1.13,
      "hs": 1.1099
    },
    {
      "Code": "IMP",
      "ib": 0.7814,
      "ab": 3.3918,
      "eb": 1.64,
      "hb": 3.6111,
      "ie": 6.4128,
      "ae": 26.4727,
      "ee": 15.95,
      "he": 24.3437,
      "is": 0.6818,
      "as": 3.7485,
      "es": 1.88,
      "hs": 3.5165
    },
    {
      "Code": "OPC",
      "ib": 0.8908,
      "ab": 2.7632,
      "eb": 1.95,
      "hb": 1.8268,
      "ie": 5.3351,
      "ae": 17.1821,
      "ee": 12.25,
      "he": 15.2482,
      "is": 0.7885,
      "as": 1.8468,
      "es": 1.35,
      "hs": 1.5781
    },
    {
      "Code": "PMC",
      "ib": 1.039,
      "ab": 3.7509,
      "eb": 1.9,
      "hb": 3.9938,
      "ie": 3.1167,
      "ae": 12.0673,
      "ee": 7.67,
      "he": 11.5212,
      "is": 0.4472,
      "as": 2.0619,
      "es": 1.24,
      "hs": 1.9428
    },
    {
      "Code": "TRA",
      "ib": 1.4484,
      "ab": 4.7614,
      "eb": 2.55,
      "hb": 2.0672,
      "ie": 6.119,
      "ae": 22.165,
      "ee": 13.53,
      "he": 12.5203,
      "is": 0.5229,
      "as": 2.6415,
      "es": 1.38,
      "hs": 1.2059
    },
    {
      "Code": "DP3",
      "ib": 1.0643,
      "ab": 3.635,
      "eb": 2.32,
      "hb": 2.1154,
      "ie": 5.56,
      "ae": 16.1815,
      "ee": 9.3,
      "he": 9.3346,
      "is": 0.5726,
      "as": 3.5944,
      "es": 1.58,
      "hs": 2.8297
    },
    {
      "Code": "DBD",
      "ib": 2.1215,
      "ab": 3.3292,
      "eb": 2.63,
      "hb": 2.9559,
      "ie": 11.7377,
      "ae": 20.4175,
      "ee": 15.42,
      "he": 17.7045,
      "is": 1.4094,
      "as": 3.168,
      "es": 1.96,
      "hs": 2.8672
    },
    {
      "Code": "AGP",
      "ib": 0.9104,
      "ab": 2.805,
      "eb": 1.34,
      "hb": 2.8972,
      "ie": 4.5763,
      "ae": 21.5271,
      "ee": 8.01,
      "he": 21.3004,
      "is": 0.3033,
      "as": 1.2742,
      "es": 0.62,
      "hs": 1.3627
    },
    {
      "Code": "DP1",
      "ib": 0.8835,
      "ab": 2.6667,
      "eb": 1.77,
      "hb": 1.4625,
      "ie": 5.749,
      "ae": 15.3174,
      "ee": 8.21,
      "he": 7.2784,
      "is": 0.0905,
      "as": 0.4049,
      "es": 0.23,
      "hs": 0.396
    },
    {
      "Code": "DVN",
      "ib": 0.2173,
      "ab": 2.3586,
      "eb": 1.56,
      "hb": 1.6744,
      "ie": 1.1812,
      "ae": 46.2583,
      "ee": 16.47,
      "he": 13.4626,
      "is": 0.4397,
      "as": 1.2547,
      "es": 0.78,
      "hs": 0.9977
    },
    {
      "Code": "MKP",
      "ib": 0.5226,
      "ab": 1.4958,
      "eb": 0.86,
      "hb": 0.5367,
      "ie": 5.6416,
      "ae": 67.0257,
      "ee": 17.89,
      "he": 52.0281,
      "is": 0.5636,
      "as": 1.2567,
      "es": 0.83,
      "hs": 0.7548
    },
    {
      "Code": "VDP",
      "ib": 0.9233,
      "ab": 1.3172,
      "eb": 1.03,
      "hb": 1.0863,
      "ie": 7.2107,
      "ae": 12.1917,
      "ee": 9.06,
      "he": 12.009,
      "is": 0.6021,
      "as": 1.2389,
      "es": 0.78,
      "hs": 0.873
    },
    {
      "Code": "DTP",
      "ib": 1.2434,
      "ab": 3.102,
      "eb": 2.37,
      "hb": 2.4849,
      "ie": 4.0431,
      "ae": 11.9977,
      "ee": 9.07,
      "he": 10.655,
      "is": 0.8157,
      "as": 2.2293,
      "es": 1.75,
      "hs": 1.8951
    },
    {
      "Code": "PBC",
      "ib": 0.591,
      "ab": 2.1923,
      "eb": 1.28,
      "hb": 0.6079,
      "ie": 13.9225,
      "ae": 209.3108,
      "ee": 41.04,
      "he": 28.1768,
      "is": 0.5818,
      "as": 2.1214,
      "es": 1.21,
      "hs": 0.7444
    }
  ],
  "ToJsonDien": [
    {
      "Code": "BTP",
      "ib": 0.2926,
      "ab": 1.5895,
      "eb": 0.74,
      "hb": 0.6756,
      "ie": -44.6896,
      "ae": 25.2053,
      "ee": 8.01,
      "he": 15.7159,
      "is": 0.1024,
      "as": 2.1736,
      "es": 0.53,
      "hs": 1.9885
    },
    {
      "Code": "HJS",
      "ib": 0,
      "ab": 2.5664,
      "eb": 1.31,
      "hb": 1.9366,
      "ie": 0,
      "ae": 16.5165,
      "ee": 10.18,
      "he": 15.7065,
      "is": 0,
      "as": 4.7936,
      "es": 2.3,
      "hs": 4.8052
    },
    {
      "Code": "NT2",
      "ib": 0.3871,
      "ab": 2.1035,
      "eb": 1.5,
      "hb": 1.4193,
      "ie": -0.3029,
      "ae": 199.9417,
      "ee": 10.83,
      "he": 20.3986,
      "is": 0.2348,
      "as": 23.4871,
      "es": 1.03,
      "hs": 0.7978
    },
    {
      "Code": "PPC",
      "ib": 0.5659,
      "ab": 2.2845,
      "eb": 1.16,
      "hb": 0.7986,
      "ie": -102.6329,
      "ae": 534.2796,
      "ee": 7.41,
      "he": 11.3509,
      "is": 0.4863,
      "as": 2.2734,
      "es": 0.95,
      "hs": 0.5062
    },
    {
      "Code": "SBA",
      "ib": 0.4056,
      "ab": 1.9795,
      "eb": 1.14,
      "hb": 1.7766,
      "ie": 5.1528,
      "ae": 75.6168,
      "ee": 9.2,
      "he": 14.6089,
      "is": 1.0831,
      "as": 16.6543,
      "es": 3.12,
      "hs": 6.2785
    },
    {
      "Code": "SEB",
      "ib": 0.7876,
      "ab": 3.8137,
      "eb": 2.36,
      "hb": 2.937,
      "ie": 3.3444,
      "ae": 14.4046,
      "ee": 9.01,
      "he": 12.405,
      "is": 1.3645,
      "as": 6.0386,
      "es": 3.69,
      "hs": 5.6726
    },
    {
      "Code": "SJD",
      "ib": 0.6643,
      "ab": 1.8764,
      "eb": 1.19,
      "hb": 1.0146,
      "ie": 3.6833,
      "ae": 12.2528,
      "ee": 7.35,
      "he": 7.5467,
      "is": 1.2973,
      "as": 3.9211,
      "es": 2.79,
      "hs": 2.4878
    },
    {
      "Code": "TBC",
      "ib": 1.5361,
      "ab": 2.4787,
      "eb": 1.84,
      "hb": 2.2892,
      "ie": 6.5969,
      "ae": 27.7443,
      "ee": 11.21,
      "he": 14.0232,
      "is": 2.886,
      "as": 7.0079,
      "es": 4.69,
      "hs": 4.4431
    },
    {
      "Code": "TMP",
      "ib": 0.8632,
      "ab": 3.6206,
      "eb": 1.94,
      "hb": 2.9162,
      "ie": -78.9372,
      "ae": 30.7926,
      "ee": 8.05,
      "he": 12.4684,
      "is": 1.8355,
      "as": 6.5386,
      "es": 3.44,
      "hs": 5.7605
    },
    {
      "Code": "VSH",
      "ib": 0.74,
      "ab": 2.5697,
      "eb": 1.22,
      "hb": 2.4219,
      "ie": 5.4975,
      "ae": 49.7953,
      "ee": 12.17,
      "he": 16.3416,
      "is": 2.9658,
      "as": 13.3511,
      "es": 6.56,
      "hs": 5.5679
    },
    {
      "Code": "GHC",
      "ib": 0.8575,
      "ab": 2.2686,
      "eb": 1.68,
      "hb": 1.319,
      "ie": 3.9781,
      "ae": 11.6972,
      "ee": 7.51,
      "he": 7.1085,
      "is": 1.8373,
      "as": 5.4962,
      "es": 3.93,
      "hs": 4.5823
    },
    {
      "Code": "SHP",
      "ib": 0.3877,
      "ab": 3.0276,
      "eb": 1.75,
      "hb": 3.036,
      "ie": 6.2475,
      "ae": 32.7981,
      "ee": 11.28,
      "he": 11.5514,
      "is": 2.8837,
      "as": 6.0287,
      "es": 3.73,
      "hs": 5.7165
    },
    {
      "Code": "CHP",
      "ib": 0.5025,
      "ab": 2.6166,
      "eb": 1.64,
      "hb": 2.6378,
      "ie": -106.7645,
      "ae": 29.1924,
      "ee": 8.7,
      "he": 12.8439,
      "is": 2.1924,
      "as": 6.5499,
      "es": 3.75,
      "hs": 5.6869
    },
    {
      "Code": "ISH",
      "ib": 0.9557,
      "ab": 2.1153,
      "eb": 1.37,
      "hb": 2.0653,
      "ie": 7.0168,
      "ae": 164.7815,
      "ee": 9.67,
      "he": 16.3391,
      "is": 2.238,
      "as": 6.1756,
      "es": 3.17,
      "hs": 6.273
    },
    {
      "Code": "ND2",
      "ib": 0.2837,
      "ab": 2.4947,
      "eb": 1.6,
      "hb": 2.2458,
      "ie": 0,
      "ae": 816.2299,
      "ee": 8.96,
      "he": 11.8005,
      "is": 1.3419,
      "as": 5.3559,
      "es": 3.47,
      "hs": 5.2127
    },
    {
      "Code": "VPD",
      "ib": 1.0117,
      "ab": 1.9755,
      "eb": 1.33,
      "hb": 1.9147,
      "ie": 8.5852,
      "ae": 50.4929,
      "ee": 12.78,
      "he": 12.9617,
      "is": 2.4188,
      "as": 5.7375,
      "es": 3.26,
      "hs": 4.6456
    },
    {
      "Code": "GEG",
      "ib": 1.0377,
      "ab": 2.5025,
      "eb": 1.39,
      "hb": 1.41,
      "ie": 7.6971,
      "ae": 49.0283,
      "ee": 17.65,
      "he": 17.1768,
      "is": 2.0053,
      "as": 7.2524,
      "es": 2.79,
      "hs": 2.5674
    },
    {
      "Code": "HND",
      "ib": 0.8518,
      "ab": 1.5806,
      "eb": 1.14,
      "hb": 0.996,
      "ie": 5.9747,
      "ae": 30.4373,
      "ee": 12.74,
      "he": 21.638,
      "is": 0.4642,
      "as": 1.05,
      "es": 0.64,
      "hs": 0.5365
    },
    {
      "Code": "QTP",
      "ib": 0.9476,
      "ab": 1.4294,
      "eb": 1.15,
      "hb": 1.1294,
      "ie": 5.0581,
      "ae": 29.6945,
      "ee": 10.5,
      "he": 10.4427,
      "is": 0.4161,
      "as": 1,
      "es": 0.54,
      "hs": 0.4999
    },
    {
      "Code": "S4A",
      "ib": 1.3864,
      "ab": 3.192,
      "eb": 2.37,
      "hb": 2.6872,
      "ie": 7.0916,
      "ae": 38.9872,
      "ee": 10.35,
      "he": 16.4312,
      "is": 2.7692,
      "as": 6.2949,
      "es": 4.65,
      "hs": 6.1338
    },
    {
      "Code": "AVC",
      "ib": 1.4809,
      "ab": 4.4005,
      "eb": 1.78,
      "hb": 3.5564,
      "ie": -604.5893,
      "ae": 343.037,
      "ee": 7.73,
      "he": 12.5829,
      "is": 2.2642,
      "as": 8.4202,
      "es": 3.99,
      "hs": 5.1487
    },
    {
      "Code": "BHA",
      "ib": 0.8428,
      "ab": 2.0532,
      "eb": 1.28,
      "hb": 1.792,
      "ie": -36.1619,
      "ae": 90.7161,
      "ee": 10.49,
      "he": 11.3024,
      "is": 2.1655,
      "as": 4.666,
      "es": 3.03,
      "hs": 4.9859
    },
    {
      "Code": "DNA",
      "ib": 0.47,
      "ab": 1.7737,
      "eb": 1.43,
      "hb": 1.5773,
      "ie": 6.7873,
      "ae": 15.896,
      "ee": 9.05,
      "he": 10.0637,
      "is": 0.467,
      "as": 0.7375,
      "es": 0.6,
      "hs": 0.5346
    },
    {
      "Code": "DNH",
      "ib": 1.3723,
      "ab": 22.1821,
      "eb": 2.45,
      "hb": 2.9157,
      "ie": 7.7448,
      "ae": 30.5442,
      "ee": 13.34,
      "he": 15.4379,
      "is": 3.8593,
      "as": 11.9552,
      "es": 6.6,
      "hs": 6.6104
    },
    {
      "Code": "HNA",
      "ib": 0.9246,
      "ab": 2.0508,
      "eb": 1.15,
      "hb": 1.7652,
      "ie": -66.1444,
      "ae": 245.9044,
      "ee": 17.78,
      "he": 18.3492,
      "is": 2.7687,
      "as": 9.1763,
      "es": 4.26,
      "hs": 6.6843
    },
    {
      "Code": "PGV",
      "ib": 0.9231,
      "ab": 2.6462,
      "eb": 1.44,
      "hb": 1.488,
      "ie": -165.6389,
      "ae": 458.7821,
      "ee": 10.55,
      "he": -167.401,
      "is": 0.2322,
      "as": 1.1027,
      "es": 0.51,
      "hs": 0.513
    },
    {
      "Code": "POW",
      "ib": 0.7847,
      "ab": 1.5213,
      "eb": 1,
      "hb": 0.9769,
      "ie": 9.393,
      "ae": 35.4545,
      "ee": 17.37,
      "he": 24.7179,
      "is": 0.2834,
      "as": 1.5301,
      "es": 1,
      "hs": 0.9815
    },
    {
      "Code": "SBH",
      "ib": 1.3994,
      "ab": 5.1795,
      "eb": 2.31,
      "hb": 3.3492,
      "ie": 4.0683,
      "ae": 22.0566,
      "ee": 10.69,
      "he": 18.1949,
      "is": 2.3757,
      "as": 9.5988,
      "es": 5.35,
      "hs": 8.7736
    },
    {
      "Code": "BSA",
      "ib": 0.9944,
      "ab": 1.655,
      "eb": 1.24,
      "hb": 1.6837,
      "ie": 5.6838,
      "ae": 46.4661,
      "ee": 9.91,
      "he": 19.4695,
      "is": 2.2154,
      "as": 4.9423,
      "es": 2.78,
      "hs": 4.9357
    },
    {
      "Code": "NTH",
      "ib": 1.9835,
      "ab": 3.7589,
      "eb": 2.78,
      "hb": 3.0196,
      "ie": 6.7946,
      "ae": 15.0726,
      "ee": 10.1,
      "he": 9.7508,
      "is": 3.1321,
      "as": 6.0187,
      "es": 3.97,
      "hs": 4.8354
    }
  ],
  "ToJsonNuoc": [
    {
      "Code": "DNW",
      "ib": 0.9832,
      "ab": 1.8564,
      "eb": 1.45,
      "hb": 1.5822,
      "ie": -23.2462,
      "ae": 36.1473,
      "ee": 11.26,
      "he": 10.9708,
      "is": 1.208,
      "as": 3.3811,
      "es": 2.01,
      "hs": 2.9144
    },
    {
      "Code": "HPW",
      "ib": 0.6388,
      "ab": 1.4928,
      "eb": 1.05,
      "hb": 1.2744,
      "ie": 8.194,
      "ae": 15.7792,
      "ee": 11.77,
      "he": 12.823,
      "is": 0.7417,
      "as": 1.3777,
      "es": 1.02,
      "hs": 1.0099
    },
    {
      "Code": "TDM",
      "ib": 1.2352,
      "ab": 2.8062,
      "eb": 1.88,
      "hb": 2.5164,
      "ie": 9.6745,
      "ae": 28.1105,
      "ee": 13.42,
      "he": 20.1831,
      "is": 4.5252,
      "as": 11.1795,
      "es": 7.63,
      "hs": 11.6495
    },
    {
      "Code": "VCW",
      "ib": 1.5891,
      "ab": 3.1262,
      "eb": 2.35,
      "hb": 2.0543,
      "ie": -167.0955,
      "ae": 62.7772,
      "ee": 12.74,
      "he": -24.8218,
      "is": 3.7212,
      "as": 7.1094,
      "es": 4.86,
      "hs": 4.0818
    },
    {
      "Code": "BWE",
      "ib": 0.739,
      "ab": 2.5099,
      "eb": 1.77,
      "hb": 2.0796,
      "ie": 6.3255,
      "ae": 23.0763,
      "ee": 12.02,
      "he": 17.4547,
      "is": 1.157,
      "as": 3.1308,
      "es": 2.35,
      "hs": 2.5911
    },
    {
      "Code": "BWS",
      "ib": 2.2591,
      "ab": 3.5767,
      "eb": 2.95,
      "hb": 3.0062,
      "ie": 8.9127,
      "ae": 15.3985,
      "ee": 12.96,
      "he": 13.3122,
      "is": 3.118,
      "as": 4.9148,
      "es": 4.36,
      "hs": 4.5699
    },
    {
      "Code": "HWS",
      "ib": 0.5909,
      "ab": 1.4364,
      "eb": 1.11,
      "hb": 1.223,
      "ie": 7.7566,
      "ae": 21.1834,
      "ee": 11.23,
      "he": 10.4511,
      "is": 1.1317,
      "as": 2.4897,
      "es": 1.85,
      "hs": 2.1028
    },
    {
      "Code": "NQN",
      "ib": 0.4219,
      "ab": 2.8018,
      "eb": 1.11,
      "hb": 1.0368,
      "ie": 5.5638,
      "ae": 32.3632,
      "ee": 14.02,
      "he": 12.2947,
      "is": 0.4517,
      "as": 4.4281,
      "es": 1.03,
      "hs": 0.8479
    },
    {
      "Code": "VIW",
      "ib": 0.5047,
      "ab": 1.8544,
      "eb": 0.96,
      "hb": 0.8782,
      "ie": -977.9742,
      "ae": 8231.5074,
      "ee": 15.08,
      "he": 74.1773,
      "is": 0.1948,
      "as": 1.2285,
      "es": 0.52,
      "hs": 0.5976
    },
    {
      "Code": "LDW",
      "ib": 0,
      "ab": 1.7261,
      "eb": 0.88,
      "hb": 1.7659,
      "ie": 0,
      "ae": 310.5618,
      "ee": 24.78,
      "he": 18.3242,
      "is": 0,
      "as": 8.3271,
      "es": 4.03,
      "hs": 5.504
    },
    {
      "Code": "PMW",
      "ib": 1.4001,
      "ab": 3.6295,
      "eb": 2.46,
      "hb": 3.1976,
      "ie": 8.8354,
      "ae": 21.7601,
      "ee": 15.28,
      "he": 19.1708,
      "is": 2.5522,
      "as": 6.1617,
      "es": 4.03,
      "hs": 5.4285
    },
    {
      "Code": "VAV",
      "ib": 1.649,
      "ab": 3.0533,
      "eb": 2.27,
      "hb": 2.3365,
      "ie": 3.608,
      "ae": 15.1004,
      "ee": 8.8,
      "he": 7.3253,
      "is": 0.9408,
      "as": 1.8659,
      "es": 1.28,
      "hs": 1.6527
    }
  ]
}